allmodes/spi_slave.v
// Koen Van Caekenberghe (koen.vancaekenberghe@chipdesign.be), ChipDesign B.V., 06.2026
// SPI Slave — all-modes variant
//
// - SPI mode: 0, 1, 2 or 3, selected by the CPOL / CPHA input pins
//     CPOL = SCK idle level, CPHA = 0: sample on leading edge / drive on trailing edge
//                            CPHA = 1: drive on leading edge / sample on trailing edge
//   CPOL/CPHA are strap or GPIO-driven configuration inputs; they are captured
//   while the FSM is in IDLE, so they must be stable before SSEL is asserted.
// - Address byte: MSB is R/nW command bit (1=Read, 0=Write); lower 7 bits are register address (0x00–0x7F)
// - Register map: 8 × 8-bit registers at addresses 0x00–0x07; reads outside this range return 0xFF
// - Register width: 1 byte
// - Secondary parallel read port (Add2_in / Data2_out) allows concurrent register readback independent of SPI
// - SCK is oversampled by Clk (two-flip-flop synchroniser + edge detection):
//   keep SCK ≤ Clk/8 (e.g. 12.5 MHz SCK at 100 MHz Clk)

`define STATE_SPI_IDLE 		3'd0
`define STATE_SPI_COMMAND	3'd1
`define STATE_SPI_WRITE 	3'd2
`define STATE_SPI_READ 		3'd3
`define STATE_SPI_END 		3'd4

`define ERROR_ADD_OUT_OF_RANGE 	8'hFF

module spi_slave
(
	input Clk,          // system clock; all internal logic is synchronous to this
	input iRST_N,       // active-low asynchronous reset

	input CPOL,         // SPI mode select: SCK idle level (mode[1])
	input CPHA,         // SPI mode select: sample/drive edge choice (mode[0])

	input SCK,          // SPI clock from master
	input MOSI,         // master-out slave-in data
	input SSEL,         // SPI slave select, active low
	output reg MISO,    // master-in slave-out data

	input [7:0] Add2_in,        // parallel read port: register address
	output reg [7:0] Data2_out, // parallel read port: register data out (updated every Clk cycle)

	output reg [7:0] debug      // sticky OR of state-machine states visited since last reset
);

reg [7:0] Register0, Register1, Register2, Register3, Register4, Register5, Register6, Register7;

reg SCK_metastable, MOSI_metastable, SSEL_metastable, CPOL_metastable, CPHA_metastable;
reg SCK_delay0, MOSI_delay0, SSEL_delay0, CPOL_delay0, CPHA_delay0;
reg SCK_delay1, SSEL_delay1;
reg CPOL_latched, CPHA_latched;
reg WrEn, RnW;
reg [3:0] BitCnt;
reg [7:0] ReceivedByte, Data_fromSPI, DataToSend, Data_toSPI, Add_SPI;
reg [2:0] SPI_State;

// SCK normalised to look like mode-0 polarity: idle low, leading edge = rising
wire SCK_norm0 = SCK_delay0 ^ CPOL_latched;
wire SCK_norm1 = SCK_delay1 ^ CPOL_latched;
wire LeadingEdge  =  SCK_norm0 & ~SCK_norm1;
wire TrailingEdge = ~SCK_norm0 &  SCK_norm1;
wire SampleEdge = CPHA_latched ? TrailingEdge : LeadingEdge;  // master has data valid here
wire DriveEdge  = CPHA_latched ? LeadingEdge  : TrailingEdge; // slave updates MISO here

always @(posedge Clk or negedge iRST_N) begin
	if(!iRST_N) begin
		Register0	<= 8'h0A;
		Register1	<= 8'h0B;
		Register2	<= 8'h0C;
		Register3	<= 8'h0D;
		Register4	<= 8'h0E;
		Register5	<= 8'h10;
		Register6	<= 8'h20;
		Register7	<= 8'h30;
		Data_toSPI 	<= 8'h00;
		Data2_out	<= 8'h00;

		SCK_metastable 	<= 1'b0;
		MOSI_metastable <= 1'b0;
		SSEL_metastable <= 1'b0;
		CPOL_metastable <= 1'b0;
		CPHA_metastable <= 1'b0;
		SCK_delay0 	<= 1'b0;
		MOSI_delay0 	<= 1'b0;
		SSEL_delay0 	<= 1'b0;
		CPOL_delay0 	<= 1'b0;
		CPHA_delay0 	<= 1'b0;
		SCK_delay1 	<= 1'b0;
		SSEL_delay1 	<= 1'b0;
		CPOL_latched	<= 1'b0;
		CPHA_latched	<= 1'b0;
		WrEn 		<= 1'b0;
		RnW		<= 1'b0;
		BitCnt		<= 4'h0;
		ReceivedByte	<= 8'h00;
		Data_fromSPI	<= 8'h00;
		DataToSend	<= 8'h00;
		Add_SPI		<= 8'h00;

		MISO		<= 1'b0;

		debug		<= 1'b0;

		SPI_State 	<= `STATE_SPI_IDLE;
	end
	else begin

		//{{{ READ/WRITE ACCESS
		if (RnW) begin
			case (Add_SPI)
				8'h00: Data_toSPI <= Register0;
				8'h01: Data_toSPI <= Register1;
				8'h02: Data_toSPI <= Register2;
				8'h03: Data_toSPI <= Register3;
				8'h04: Data_toSPI <= Register4;
				8'h05: Data_toSPI <= Register5;
				8'h06: Data_toSPI <= Register6;
				8'h07: Data_toSPI <= Register7;
				default: Data_toSPI <= `ERROR_ADD_OUT_OF_RANGE;
			endcase
		end
		else if (WrEn) begin
			case (Add_SPI)
				8'h00:  Register0 <= Data_fromSPI;
				8'h01:  Register1 <= Data_fromSPI;
				8'h02:  Register2 <= Data_fromSPI;
				8'h03:  Register3 <= Data_fromSPI;
				8'h04:  Register4 <= Data_fromSPI;
				8'h05:  Register5 <= Data_fromSPI;
				8'h06:  Register6 <= Data_fromSPI;
				8'h07:  Register7 <= Data_fromSPI;
			endcase
		end
		//}}}

		//{{{ READ ACCESS 2
		case (Add2_in)
			8'h00: Data2_out <= Register0;
			8'h01: Data2_out <= Register1;
			8'h02: Data2_out <= Register2;
			8'h03: Data2_out <= Register3;
			8'h04: Data2_out <= Register4;
			8'h05: Data2_out <= Register5;
			8'h06: Data2_out <= Register6;
			8'h07: Data2_out <= Register7;
			default: Data2_out <= `ERROR_ADD_OUT_OF_RANGE;
		endcase
		//}}}

		//{{{ SPI INTERFACE
		// Two-stage synchroniser: captures async SPI inputs into Clk domain to prevent metastability
		SCK_metastable 	<= SCK;
		MOSI_metastable <= MOSI;
		SSEL_metastable <= SSEL;
		CPOL_metastable <= CPOL;
		CPHA_metastable <= CPHA;
		SCK_delay0 	<= SCK_metastable;
		MOSI_delay0 	<= MOSI_metastable;
		SSEL_delay0 	<= SSEL_metastable;
		CPOL_delay0 	<= CPOL_metastable;
		CPHA_delay0 	<= CPHA_metastable;
		SCK_delay1 	<= SCK_delay0;
		SSEL_delay1 	<= SSEL_delay0;

		WrEn 		<= 1'b0;

		case (SPI_State)

			`STATE_SPI_IDLE: begin
				BitCnt <= 0;
				// Mode pins are only taken over while idle so a transaction
				// always runs with a consistent CPOL/CPHA pair
				CPOL_latched <= CPOL_delay0;
				CPHA_latched <= CPHA_delay0;
				debug <= debug | 1;
				if (SSEL_delay0 == 0  && SSEL_delay1 == 1)
					SPI_State <= `STATE_SPI_COMMAND;
			end

			`STATE_SPI_COMMAND: begin
				debug <= debug | 8'h02;
				if (SampleEdge) begin
					ReceivedByte <= {ReceivedByte[6:0], MOSI_delay0};
					BitCnt <= BitCnt + 1;
				end
				if (BitCnt == 4'h8) begin
					BitCnt 	<= 4'h0;
					Add_SPI	<= {1'b0, ReceivedByte[6:0]};
					RnW 	<= ReceivedByte[7];
					if (ReceivedByte[7] == 1)
						SPI_State <= `STATE_SPI_READ;
					else
						SPI_State <= `STATE_SPI_WRITE;
				end
			end

			`STATE_SPI_WRITE: begin
				debug <= debug | 4;
				if (SampleEdge) begin
					ReceivedByte <= {ReceivedByte[6:0], MOSI_delay0};
					BitCnt <= BitCnt + 1;
				end
				if (BitCnt == 4'h8) begin
					WrEn <= 1;
					Data_fromSPI <= ReceivedByte;
					SPI_State <= `STATE_SPI_END;
				end
			end

			`STATE_SPI_READ: begin
				debug <= debug | 8;
				if (BitCnt == 0) begin
					if (DriveEdge) begin
						MISO <= Data_toSPI[7];
						DataToSend <= {Data_toSPI[6:0], 1'b0};
						BitCnt <= 1;
					end
				end
				else begin
					if (DriveEdge) begin
						MISO <= DataToSend[7];
						DataToSend <= {DataToSend[6:0], 1'b0};
						BitCnt <= BitCnt + 1;
					end
				end
				if (BitCnt == 4'h8) begin
					Data_fromSPI <= ReceivedByte;
					SPI_State <= `STATE_SPI_END;
				end
			end

			`STATE_SPI_END: begin
				debug <= debug | 16;
				if (SSEL_delay0)
					SPI_State <= `STATE_SPI_IDLE;
			end

		endcase
		//}}}

	end
end

endmodule

allmodes/tb_spi_slave_aurix.v
// Koen Van Caekenberghe (koen.vancaekenberghe@chipdesign.be), ChipDesign B.V., 08.2026
// Host verification test bench — Infineon AURIX QSPI master model
//
// Models an AURIX (TC2xx/TC3xx) QSPI module driving one SLSO chip-select:
//   - 100 MHz DUT system clock (10 ns period, as constrained in flow/constraint.sdc)
//   - 12.5 MHz SCLK (80 ns period) — the SCK <= Clk/8 limit of this slave
//   - SLSO lead delay (tLEAD) of one SCLK period before the first clock edge
//     and trail delay (tTRAIL) of one SCLK period after the last one
//   - Inter-word idle of one SCLK period between the command and data bytes
//     (QSPI idle delay between data words, SLSO kept asserted)
//   - MSB first, clock polarity/phase per SPI mode (ECON/iLLD mode settings)
//
// Per mode, after a DUT reset — full register-map verification:
//   1. WRITE a distinct value {mode,3'b101,i} to every register i = 0..7
//   2. READ every register back over SPI and compare
//   3. Read every register through the parallel port and compare
//   4. READ out-of-range address 0x7F -> expect 0xFF
//   5. Check debug = 0x1F (all five FSM states visited)
//
// Compile for RTL:
//   iverilog -g2012 -o tb_aurix_rtl.out tb_spi_slave_aurix.v && vvp tb_aurix_rtl.out
// Compile for synthesised netlist:
//   iverilog -g2012 -DSYNTH -o tb_aurix_syn.out flow/spi_slave_synth.v tb_spi_slave_aurix.v
//   vvp tb_aurix_syn.out

`timescale 1ns/1ns

`ifndef SYNTH
`include "spi_slave.v"
`endif

module tb_spi_slave_aurix();

// DUT system clock: 100 MHz
reg clk;
initial begin
    clk = 0;
    forever #5 clk = ~clk;
end

// QSPI timing: 12.5 MHz SCLK, tLEAD = tTRAIL = inter-word idle = 1 SCLK period
localparam SCK_HALF = 40;
localparam T_LEAD   = 80;
localparam T_TRAIL  = 80;
localparam T_IDLE   = 80;

reg [7:0] addr;
wire [7:0] data;
wire [7:0] debug;
wire miso;
reg mosi;
reg rst_n;
reg sck;
reg ssel;
reg cpol, cpha;

reg [7:0] rx0, rx1;   // received bytes of the current frame
integer errors;
integer mode;
integer i;
reg [7:0] wr_val;

spi_slave spi_slave1(
    .Clk(clk),
    .iRST_N(rst_n),
    .CPOL(cpol),
    .CPHA(cpha),
    .SCK(sck),
    .MOSI(mosi),
    .SSEL(ssel),
    .MISO(miso),
    .Add2_in(addr),
    .Data2_out(data),
    .debug(debug)
);

// One byte on the wire, MSB first, in the currently selected mode.
task spi_clock_byte;
    input  [7:0] tx;
    output [7:0] rx;
    integer k;
    begin
        for (k = 7; k >= 0; k = k - 1) begin
            if (cpha == 0) begin
                mosi = tx[k];
                #(SCK_HALF) sck = ~cpol;   // leading edge: both sides sample
                rx[k] = miso;
                #(SCK_HALF) sck = cpol;    // trailing edge: shift
            end
            else begin
                sck = ~cpol;               // leading edge: both sides shift
                mosi = tx[k];
                #(SCK_HALF) sck = cpol;    // trailing edge: both sides sample
                rx[k] = miso;
                #(SCK_HALF);
            end
        end
    end
endtask

// QSPI frame: SLSO low with lead delay, command byte, inter-word idle,
// data byte, trail delay, SLSO high.
task qspi_frame;
    input  [7:0] tx0;
    input  [7:0] tx1;
    begin
        ssel = 0;
        #(T_LEAD);
        spi_clock_byte(tx0, rx0);
        #(T_IDLE);
        spi_clock_byte(tx1, rx1);
        #(T_TRAIL);
        ssel = 1;
        #(2*SCK_HALF);   // pause until next frame
    end
endtask

task check_byte;
    input [8*40:1] label;
    input [7:0] got;
    input [7:0] expect_v;
    begin
        if (got !== expect_v) begin
            $display("FAIL mode %0d %0s: expected 0x%02X, got 0x%02X", mode, label, expect_v, got);
            errors = errors + 1;
        end
    end
endtask

task run_mode;
    input [1:0] m;
    begin
        cpol  = m[1];
        cpha  = m[0];
        addr  = 8'd0;
        mosi  = 0;
        ssel  = 1;
        rst_n = 0;
        sck   = m[1];
        #100 rst_n = 1;
        #100;

        // 1. WRITE all 8 registers
        for (i = 0; i < 8; i = i + 1) begin
            wr_val = {m, 3'b101, i[2:0]};
            qspi_frame({1'b0, i[6:0]}, wr_val);
        end

        // 2. READ all 8 registers back over SPI
        for (i = 0; i < 8; i = i + 1) begin
            wr_val = {m, 3'b101, i[2:0]};
            qspi_frame({1'b1, i[6:0]}, 8'h00);
            check_byte("SPI read-back", rx1, wr_val);
        end

        // 3. Read all 8 registers through the parallel port
        for (i = 0; i < 8; i = i + 1) begin
            wr_val = {m, 3'b101, i[2:0]};
            addr = i[7:0];
            #50;
            check_byte("parallel read", data, wr_val);
        end

        // 4. READ out-of-range address 0x7F
        qspi_frame(8'hFF, 8'h00);
        check_byte("out-of-range read", rx1, 8'hFF);

        // 5. All FSM states visited
        check_byte("debug", debug, 8'h1F);

        $display("MODE %0d (CPOL=%0d CPHA=%0d) %0t: 8 regs written+read back, parallel port ok, oor=0x%02X debug=0x%02X",
                 m, m[1], m[0], $time, rx1, debug);
    end
endtask

initial begin
    errors = 0;
    for (mode = 0; mode <= 3; mode = mode + 1)
        run_mode(mode[1:0]);

    if (errors == 0)
        $display("PASS: AURIX QSPI master model — all checks passed in all 4 SPI modes");
    else
        $display("FAIL: %0d check(s) failed", errors);
    #100 $finish;
end

initial begin
`ifdef SYNTH
    $dumpfile("tb_spi_slave_aurix_synth.vcd");
`else
    $dumpfile("tb_spi_slave_aurix.vcd");
`endif
    $dumpvars(0, tb_spi_slave_aurix);
end

endmodule

allmodes/tb_spi_slave_aurix.vcd
$date
	Sat Aug  8 21:53:38 2026
$end
$version
	Icarus Verilog
$end
$timescale
	1ns
$end
$scope module tb_spi_slave_aurix $end
$var wire 1 ! miso $end
$var wire 8 " debug [7:0] $end
$var wire 8 # data [7:0] $end
$var parameter 32 $ SCK_HALF $end
$var parameter 32 % T_IDLE $end
$var parameter 32 & T_LEAD $end
$var parameter 32 ' T_TRAIL $end
$var reg 8 ( addr [7:0] $end
$var reg 1 ) clk $end
$var reg 1 * cpha $end
$var reg 1 + cpol $end
$var reg 1 , mosi $end
$var reg 1 - rst_n $end
$var reg 8 . rx0 [7:0] $end
$var reg 8 / rx1 [7:0] $end
$var reg 1 0 sck $end
$var reg 1 1 ssel $end
$var reg 8 2 wr_val [7:0] $end
$var integer 32 3 errors [31:0] $end
$var integer 32 4 i [31:0] $end
$var integer 32 5 mode [31:0] $end
$scope module spi_slave1 $end
$var wire 8 6 Add2_in [7:0] $end
$var wire 1 * CPHA $end
$var wire 1 + CPOL $end
$var wire 1 ) Clk $end
$var wire 1 7 LeadingEdge $end
$var wire 1 , MOSI $end
$var wire 1 0 SCK $end
$var wire 1 8 SCK_norm0 $end
$var wire 1 9 SCK_norm1 $end
$var wire 1 1 SSEL $end
$var wire 1 : TrailingEdge $end
$var wire 1 - iRST_N $end
$var wire 1 ; SampleEdge $end
$var wire 1 < DriveEdge $end
$var reg 8 = Add_SPI [7:0] $end
$var reg 4 > BitCnt [3:0] $end
$var reg 1 ? CPHA_delay0 $end
$var reg 1 @ CPHA_latched $end
$var reg 1 A CPHA_metastable $end
$var reg 1 B CPOL_delay0 $end
$var reg 1 C CPOL_latched $end
$var reg 1 D CPOL_metastable $end
$var reg 8 E Data2_out [7:0] $end
$var reg 8 F DataToSend [7:0] $end
$var reg 8 G Data_fromSPI [7:0] $end
$var reg 8 H Data_toSPI [7:0] $end
$var reg 1 ! MISO $end
$var reg 1 I MOSI_delay0 $end
$var reg 1 J MOSI_metastable $end
$var reg 8 K ReceivedByte [7:0] $end
$var reg 8 L Register0 [7:0] $end
$var reg 8 M Register1 [7:0] $end
$var reg 8 N Register2 [7:0] $end
$var reg 8 O Register3 [7:0] $end
$var reg 8 P Register4 [7:0] $end
$var reg 8 Q Register5 [7:0] $end
$var reg 8 R Register6 [7:0] $end
$var reg 8 S Register7 [7:0] $end
$var reg 1 T RnW $end
$var reg 1 U SCK_delay0 $end
$var reg 1 V SCK_delay1 $end
$var reg 1 W SCK_metastable $end
$var reg 3 X SPI_State [2:0] $end
$var reg 1 Y SSEL_delay0 $end
$var reg 1 Z SSEL_delay1 $end
$var reg 1 [ SSEL_metastable $end
$var reg 1 \ WrEn $end
$var reg 8 ] debug [7:0] $end
$upscope $end
$scope task check_byte $end
$var reg 8 ^ expect_v [7:0] $end
$var reg 8 _ got [7:0] $end
$var reg 320 ` label [320:1] $end
$upscope $end
$scope task qspi_frame $end
$var reg 8 a tx0 [7:0] $end
$var reg 8 b tx1 [7:0] $end
$upscope $end
$scope task run_mode $end
$var reg 2 c m [1:0] $end
$upscope $end
$scope task spi_clock_byte $end
$var reg 8 d rx [7:0] $end
$var reg 8 e tx [7:0] $end
$var integer 32 f k [31:0] $end
$upscope $end
$upscope $end
$enddefinitions $end
$comment Show the parameter values. $end
$dumpall
b1010000 '
b1010000 &
b1010000 %
b101000 $
$end
#0
$dumpvars
bx f
bx e
bx d
b0 c
bx b
bx a
bx `
bx _
bx ^
b0 ]
0\
0[
0Z
0Y
b0 X
0W
0V
0U
0T
b110000 S
b100000 R
b10000 Q
b1110 P
b1101 O
b1100 N
b1011 M
b1010 L
b0 K
0J
0I
b0 H
b0 G
b0 F
b0 E
0D
0C
0B
0A
0@
0?
b0 >
b0 =
0<
0;
0:
09
08
07
b0 6
b0 5
bx 4
b0 3
bx 2
11
00
bx /
bx .
0-
0,
0+
0*
0)
b0 (
b0 #
b0 "
0!
$end
#5
1)
#10
0)
#15
1)
#20
0)
#25
1)
#30
0)
#35
1)
#40
0)
#45
1)
#50
0)
#55
1)
#60
0)
#65
1)
#70
0)
#75
1)
#80
0)
#85
1)
#90
0)
#95
1)
#100
0)
1-
#105
b1 "
b1 ]
1[
b1010 #
b1010 E
1)
#110
0)
#115
1Y
1)
#120
0)
#125
1Z
1)
#130
0)
#135
1)
#140
0)
#145
1)
#150
0)
#155
1)
#160
0)
#165
1)
#170
0)
#175
1)
#180
0)
#185
1)
#190
0)
#195
1)
#200
0)
01
b101000 b
b0 a
b101000 2
b0 4
#205
0[
1)
#210
0)
#215
0Y
1)
#220
0)
#225
b1 X
0Z
1)
#230
0)
#235
b11 "
b11 ]
1)
#240
0)
#245
1)
#250
0)
#255
1)
#260
0)
#265
1)
#270
0)
#275
1)
#280
0)
b111 f
b0 e
#285
1)
#290
0)
#295
1)
#300
0)
#305
1)
#310
0)
#315
1)
#320
0)
b0xxxxxxx d
10
#325
1W
1)
#330
0)
#335
1;
17
18
1U
1)
#340
0)
#345
0;
07
19
b1 >
1V
1)
#350
0)
#355
1)
#360
0)
b110 f
00
#365
0W
1)
#370
0)
#375
1<
1:
08
0U
1)
#380
0)
#385
0<
0:
09
0V
1)
#390
0)
#395
1)
#400
0)
b0xxxxxx d
10
#405
1W
1)
#410
0)
#415
1;
17
18
1U
1)
#420
0)
#425
0;
07
19
b10 >
1V
1)
#430
0)
#435
1)
#440
0)
b101 f
00
#445
0W
1)
#450
0)
#455
1<
1:
08
0U
1)
#460
0)
#465
0<
0:
09
0V
1)
#470
0)
#475
1)
#480
0)
b0xxxxx d
10
#485
1W
1)
#490
0)
#495
1;
17
18
1U
1)
#500
0)
#505
0;
07
19
b11 >
1V
1)
#510
0)
#515
1)
#520
0)
b100 f
00
#525
0W
1)
#530
0)
#535
1<
1:
08
0U
1)
#540
0)
#545
0<
0:
09
0V
1)
#550
0)
#555
1)
#560
0)
b0xxxx d
10
#565
1W
1)
#570
0)
#575
1;
17
18
1U
1)
#580
0)
#585
0;
07
19
b100 >
1V
1)
#590
0)
#595
1)
#600
0)
b11 f
00
#605
0W
1)
#610
0)
#615
1<
1:
08
0U
1)
#620
0)
#625
0<
0:
09
0V
1)
#630
0)
#635
1)
#640
0)
b0xxx d
10
#645
1W
1)
#650
0)
#655
1;
17
18
1U
1)
#660
0)
#665
0;
07
19
b101 >
1V
1)
#670
0)
#675
1)
#680
0)
b10 f
00
#685
0W
1)
#690
0)
#695
1<
1:
08
0U
1)
#700
0)
#705
0<
0:
09
0V
1)
#710
0)
#715
1)
#720
0)
b0xx d
10
#725
1W
1)
#730
0)
#735
1;
17
18
1U
1)
#740
0)
#745
0;
07
19
b110 >
1V
1)
#750
0)
#755
1)
#760
0)
b1 f
00
#765
0W
1)
#770
0)
#775
1<
1:
08
0U
1)
#780
0)
#785
0<
0:
09
0V
1)
#790
0)
#795
1)
#800
0)
b0x d
10
#805
1W
1)
#810
0)
#815
1;
17
18
1U
1)
#820
0)
#825
0;
07
19
b111 >
1V
1)
#830
0)
#835
1)
#840
0)
b0 f
00
#845
0W
1)
#850
0)
#855
1<
1:
08
0U
1)
#860
0)
#865
0<
0:
09
0V
1)
#870
0)
#875
1)
#880
0)
b0 d
10
#885
1W
1)
#890
0)
#895
1;
17
18
1U
1)
#900
0)
#905
0;
07
19
b1000 >
1V
1)
#910
0)
#915
b10 X
b0 >
1)
#920
0)
b0 .
b11111111111111111111111111111111 f
00
#925
b111 "
b111 ]
0W
1)
#930
0)
#935
1<
1:
08
0U
1)
#940
0)
#945
0<
0:
09
0V
1)
#950
0)
#955
1)
#960
0)
#965
1)
#970
0)
#975
1)
#980
0)
#985
1)
#990
0)
#995
1)
#1000
0)
b111 f
b101000 e
#1005
1)
#1010
0)
#1015
1)
#1020
0)
#1025
1)
#1030
0)
#1035
1)
#1040
0)
10
#1045
1W
1)
#1050
0)
#1055
1;
17
18
1U
1)
#1060
0)
#1065
0;
07
19
b1 >
1V
1)
#1070
0)
#1075
1)
#1080
0)
b110 f
00
#1085
0W
1)
#1090
0)
#1095
1<
1:
08
0U
1)
#1100
0)
#1105
0<
0:
09
0V
1)
#1110
0)
#1115
1)
#1120
0)
10
#1125
1W
1)
#1130
0)
#1135
1;
17
18
1U
1)
#1140
0)
#1145
0;
07
19
b10 >
1V
1)
#1150
0)
#1155
1)
#1160
0)
1,
b101 f
00
#1165
1J
0W
1)
#1170
0)
#1175
1<
1:
08
1I
0U
1)
#1180
0)
#1185
0<
0:
09
0V
1)
#1190
0)
#1195
1)
#1200
0)
10
#1205
1W
1)
#1210
0)
#1215
1;
17
18
1U
1)
#1220
0)
#1225
0;
07
19
b11 >
b1 K
1V
1)
#1230
0)
#1235
1)
#1240
0)
0,
b100 f
00
#1245
0J
0W
1)
#1250
0)
#1255
1<
1:
08
0I
0U
1)
#1260
0)
#1265
0<
0:
09
0V
1)
#1270
0)
#1275
1)
#1280
0)
10
#1285
1W
1)
#1290
0)
#1295
1;
17
18
1U
1)
#1300
0)
#1305
0;
07
19
b100 >
b10 K
1V
1)
#1310
0)
#1315
1)
#1320
0)
1,
b11 f
00
#1325
1J
0W
1)
#1330
0)
#1335
1<
1:
08
1I
0U
1)
#1340
0)
#1345
0<
0:
09
0V
1)
#1350
0)
#1355
1)
#1360
0)
10
#1365
1W
1)
#1370
0)
#1375
1;
17
18
1U
1)
#1380
0)
#1385
0;
07
19
b101 >
b101 K
1V
1)
#1390
0)
#1395
1)
#1400
0)
0,
b10 f
00
#1405
0J
0W
1)
#1410
0)
#1415
1<
1:
08
0I
0U
1)
#1420
0)
#1425
0<
0:
09
0V
1)
#1430
0)
#1435
1)
#1440
0)
10
#1445
1W
1)
#1450
0)
#1455
1;
17
18
1U
1)
#1460
0)
#1465
0;
07
19
b110 >
b1010 K
1V
1)
#1470
0)
#1475
1)
#1480
0)
b1 f
00
#1485
0W
1)
#1490
0)
#1495
1<
1:
08
0U
1)
#1500
0)
#1505
0<
0:
09
0V
1)
#1510
0)
#1515
1)
#1520
0)
10
#1525
1W
1)
#1530
0)
#1535
1;
17
18
1U
1)
#1540
0)
#1545
0;
07
19
b111 >
b10100 K
1V
1)
#1550
0)
#1555
1)
#1560
0)
b0 f
00
#1565
0W
1)
#1570
0)
#1575
1<
1:
08
0U
1)
#1580
0)
#1585
0<
0:
09
0V
1)
#1590
0)
#1595
1)
#1600
0)
10
#1605
1W
1)
#1610
0)
#1615
1;
17
18
1U
1)
#1620
0)
#1625
0;
07
19
b1000 >
b101000 K
1V
1)
#1630
0)
#1635
b100 X
b101000 G
1\
1)
#1640
0)
b0 /
b11111111111111111111111111111111 f
00
#1645
b10111 "
b10111 ]
0\
0W
b101000 L
1)
#1650
0)
#1655
1<
1:
08
0U
b101000 #
b101000 E
1)
#1660
0)
#1665
0<
0:
09
0V
1)
#1670
0)
#1675
1)
#1680
0)
#1685
1)
#1690
0)
#1695
1)
#1700
0)
#1705
1)
#1710
0)
#1715
1)
#1720
0)
11
#1725
1[
1)
#1730
0)
#1735
1Y
1)
#1740
0)
#1745
b0 X
1Z
1)
#1750
0)
#1755
b0 >
1)
#1760
0)
#1765
1)
#1770
0)
#1775
1)
#1780
0)
#1785
1)
#1790
0)
#1795
1)
#1800
0)
01
b101001 b
b1 a
b101001 2
b1 4
#1805
0[
1)
#1810
0)
#1815
0Y
1)
#1820
0)
#1825
b1 X
0Z
1)
#1830
0)
#1835
1)
#1840
0)
#1845
1)
#1850
0)
#1855
1)
#1860
0)
#1865
1)
#1870
0)
#1875
1)
#1880
0)
b111 f
b1 e
#1885
1)
#1890
0)
#1895
1)
#1900
0)
#1905
1)
#1910
0)
#1915
1)
#1920
0)
10
#1925
1W
1)
#1930
0)
#1935
1;
17
18
1U
1)
#1940
0)
#1945
0;
07
19
b1 >
b1010000 K
1V
1)
#1950
0)
#1955
1)
#1960
0)
b110 f
00
#1965
0W
1)
#1970
0)
#1975
1<
1:
08
0U
1)
#1980
0)
#1985
0<
0:
09
0V
1)
#1990
0)
#1995
1)
#2000
0)
10
#2005
1W
1)
#2010
0)
#2015
1;
17
18
1U
1)
#2020
0)
#2025
0;
07
19
b10 >
b10100000 K
1V
1)
#2030
0)
#2035
1)
#2040
0)
b101 f
00
#2045
0W
1)
#2050
0)
#2055
1<
1:
08
0U
1)
#2060
0)
#2065
0<
0:
09
0V
1)
#2070
0)
#2075
1)
#2080
0)
10
#2085
1W
1)
#2090
0)
#2095
1;
17
18
1U
1)
#2100
0)
#2105
0;
07
19
b11 >
b1000000 K
1V
1)
#2110
0)
#2115
1)
#2120
0)
b100 f
00
#2125
0W
1)
#2130
0)
#2135
1<
1:
08
0U
1)
#2140
0)
#2145
0<
0:
09
0V
1)
#2150
0)
#2155
1)
#2160
0)
10
#2165
1W
1)
#2170
0)
#2175
1;
17
18
1U
1)
#2180
0)
#2185
0;
07
19
b100 >
b10000000 K
1V
1)
#2190
0)
#2195
1)
#2200
0)
b11 f
00
#2205
0W
1)
#2210
0)
#2215
1<
1:
08
0U
1)
#2220
0)
#2225
0<
0:
09
0V
1)
#2230
0)
#2235
1)
#2240
0)
10
#2245
1W
1)
#2250
0)
#2255
1;
17
18
1U
1)
#2260
0)
#2265
0;
07
19
b101 >
b0 K
1V
1)
#2270
0)
#2275
1)
#2280
0)
b10 f
00
#2285
0W
1)
#2290
0)
#2295
1<
1:
08
0U
1)
#2300
0)
#2305
0<
0:
09
0V
1)
#2310
0)
#2315
1)
#2320
0)
10
#2325
1W
1)
#2330
0)
#2335
1;
17
18
1U
1)
#2340
0)
#2345
0;
07
19
b110 >
1V
1)
#2350
0)
#2355
1)
#2360
0)
b1 f
00
#2365
0W
1)
#2370
0)
#2375
1<
1:
08
0U
1)
#2380
0)
#2385
0<
0:
09
0V
1)
#2390
0)
#2395
1)
#2400
0)
10
#2405
1W
1)
#2410
0)
#2415
1;
17
18
1U
1)
#2420
0)
#2425
0;
07
19
b111 >
1V
1)
#2430
0)
#2435
1)
#2440
0)
1,
b0 f
00
#2445
1J
0W
1)
#2450
0)
#2455
1<
1:
08
1I
0U
1)
#2460
0)
#2465
0<
0:
09
0V
1)
#2470
0)
#2475
1)
#2480
0)
10
#2485
1W
1)
#2490
0)
#2495
1;
17
18
1U
1)
#2500
0)
#2505
0;
07
19
b1000 >
b1 K
1V
1)
#2510
0)
#2515
b10 X
b1 =
b0 >
1)
#2520
0)
b11111111111111111111111111111111 f
00
#2525
0W
1)
#2530
0)
#2535
1<
1:
08
0U
1)
#2540
0)
#2545
0<
0:
09
0V
1)
#2550
0)
#2555
1)
#2560
0)
#2565
1)
#2570
0)
#2575
1)
#2580
0)
#2585
1)
#2590
0)
#2595
1)
#2600
0)
0,
b111 f
b101001 e
#2605
0J
1)
#2610
0)
#2615
0I
1)
#2620
0)
#2625
1)
#2630
0)
#2635
1)
#2640
0)
10
#2645
1W
1)
#2650
0)
#2655
1;
17
18
1U
1)
#2660
0)
#2665
0;
07
19
b1 >
b10 K
1V
1)
#2670
0)
#2675
1)
#2680
0)
b110 f
00
#2685
0W
1)
#2690
0)
#2695
1<
1:
08
0U
1)
#2700
0)
#2705
0<
0:
09
0V
1)
#2710
0)
#2715
1)
#2720
0)
10
#2725
1W
1)
#2730
0)
#2735
1;
17
18
1U
1)
#2740
0)
#2745
0;
07
19
b10 >
b100 K
1V
1)
#2750
0)
#2755
1)
#2760
0)
1,
b101 f
00
#2765
1J
0W
1)
#2770
0)
#2775
1<
1:
08
1I
0U
1)
#2780
0)
#2785
0<
0:
09
0V
1)
#2790
0)
#2795
1)
#2800
0)
10
#2805
1W
1)
#2810
0)
#2815
1;
17
18
1U
1)
#2820
0)
#2825
0;
07
19
b11 >
b1001 K
1V
1)
#2830
0)
#2835
1)
#2840
0)
0,
b100 f
00
#2845
0J
0W
1)
#2850
0)
#2855
1<
1:
08
0I
0U
1)
#2860
0)
#2865
0<
0:
09
0V
1)
#2870
0)
#2875
1)
#2880
0)
10
#2885
1W
1)
#2890
0)
#2895
1;
17
18
1U
1)
#2900
0)
#2905
0;
07
19
b100 >
b10010 K
1V
1)
#2910
0)
#2915
1)
#2920
0)
1,
b11 f
00
#2925
1J
0W
1)
#2930
0)
#2935
1<
1:
08
1I
0U
1)
#2940
0)
#2945
0<
0:
09
0V
1)
#2950
0)
#2955
1)
#2960
0)
10
#2965
1W
1)
#2970
0)
#2975
1;
17
18
1U
1)
#2980
0)
#2985
0;
07
19
b101 >
b100101 K
1V
1)
#2990
0)
#2995
1)
#3000
0)
0,
b10 f
00
#3005
0J
0W
1)
#3010
0)
