allmodes/spi_slave.v
// Koen Van Caekenberghe (koen.vancaekenberghe@chipdesign.be), ChipDesign B.V., 06.2026
// SPI Slave — all-modes variant
//
// - SPI mode: 0, 1, 2 or 3, selected by the CPOL / CPHA input pins
//     CPOL = SCK idle level, CPHA = 0: sample on leading edge / drive on trailing edge
//                            CPHA = 1: drive on leading edge / sample on trailing edge
//   CPOL/CPHA are strap or GPIO-driven configuration inputs; they are captured
//   while the FSM is in IDLE, so they must be stable before SSEL is asserted.
// - Address byte: MSB is R/nW command bit (1=Read, 0=Write); lower 7 bits are register address (0x00–0x7F)
// - Register map: 8 × 8-bit registers at addresses 0x00–0x07; reads outside this range return 0xFF
// - Register width: 1 byte
// - Secondary parallel read port (Add2_in / Data2_out) allows concurrent register readback independent of SPI
// - SCK is oversampled by Clk (two-flip-flop synchroniser + edge detection):
//   keep SCK ≤ Clk/8 (e.g. 12.5 MHz SCK at 100 MHz Clk)

`define STATE_SPI_IDLE 		3'd0
`define STATE_SPI_COMMAND	3'd1
`define STATE_SPI_WRITE 	3'd2
`define STATE_SPI_READ 		3'd3
`define STATE_SPI_END 		3'd4

`define ERROR_ADD_OUT_OF_RANGE 	8'hFF

module spi_slave
(
	input Clk,          // system clock; all internal logic is synchronous to this
	input iRST_N,       // active-low asynchronous reset

	input CPOL,         // SPI mode select: SCK idle level (mode[1])
	input CPHA,         // SPI mode select: sample/drive edge choice (mode[0])

	input SCK,          // SPI clock from master
	input MOSI,         // master-out slave-in data
	input SSEL,         // SPI slave select, active low
	output reg MISO,    // master-in slave-out data

	input [7:0] Add2_in,        // parallel read port: register address
	output reg [7:0] Data2_out, // parallel read port: register data out (updated every Clk cycle)

	output reg [7:0] debug      // sticky OR of state-machine states visited since last reset
);

reg [7:0] Register0, Register1, Register2, Register3, Register4, Register5, Register6, Register7;

reg SCK_metastable, MOSI_metastable, SSEL_metastable, CPOL_metastable, CPHA_metastable;
reg SCK_delay0, MOSI_delay0, SSEL_delay0, CPOL_delay0, CPHA_delay0;
reg SCK_delay1, SSEL_delay1;
reg CPOL_latched, CPHA_latched;
reg WrEn, RnW;
reg [3:0] BitCnt;
reg [7:0] ReceivedByte, Data_fromSPI, DataToSend, Data_toSPI, Add_SPI;
reg [2:0] SPI_State;

// SCK normalised to look like mode-0 polarity: idle low, leading edge = rising
wire SCK_norm0 = SCK_delay0 ^ CPOL_latched;
wire SCK_norm1 = SCK_delay1 ^ CPOL_latched;
wire LeadingEdge  =  SCK_norm0 & ~SCK_norm1;
wire TrailingEdge = ~SCK_norm0 &  SCK_norm1;
wire SampleEdge = CPHA_latched ? TrailingEdge : LeadingEdge;  // master has data valid here
wire DriveEdge  = CPHA_latched ? LeadingEdge  : TrailingEdge; // slave updates MISO here

always @(posedge Clk or negedge iRST_N) begin
	if(!iRST_N) begin
		Register0	<= 8'h0A;
		Register1	<= 8'h0B;
		Register2	<= 8'h0C;
		Register3	<= 8'h0D;
		Register4	<= 8'h0E;
		Register5	<= 8'h10;
		Register6	<= 8'h20;
		Register7	<= 8'h30;
		Data_toSPI 	<= 8'h00;
		Data2_out	<= 8'h00;

		SCK_metastable 	<= 1'b0;
		MOSI_metastable <= 1'b0;
		SSEL_metastable <= 1'b0;
		CPOL_metastable <= 1'b0;
		CPHA_metastable <= 1'b0;
		SCK_delay0 	<= 1'b0;
		MOSI_delay0 	<= 1'b0;
		SSEL_delay0 	<= 1'b0;
		CPOL_delay0 	<= 1'b0;
		CPHA_delay0 	<= 1'b0;
		SCK_delay1 	<= 1'b0;
		SSEL_delay1 	<= 1'b0;
		CPOL_latched	<= 1'b0;
		CPHA_latched	<= 1'b0;
		WrEn 		<= 1'b0;
		RnW		<= 1'b0;
		BitCnt		<= 4'h0;
		ReceivedByte	<= 8'h00;
		Data_fromSPI	<= 8'h00;
		DataToSend	<= 8'h00;
		Add_SPI		<= 8'h00;

		MISO		<= 1'b0;

		debug		<= 1'b0;

		SPI_State 	<= `STATE_SPI_IDLE;
	end
	else begin

		//{{{ READ/WRITE ACCESS
		if (RnW) begin
			case (Add_SPI)
				8'h00: Data_toSPI <= Register0;
				8'h01: Data_toSPI <= Register1;
				8'h02: Data_toSPI <= Register2;
				8'h03: Data_toSPI <= Register3;
				8'h04: Data_toSPI <= Register4;
				8'h05: Data_toSPI <= Register5;
				8'h06: Data_toSPI <= Register6;
				8'h07: Data_toSPI <= Register7;
				default: Data_toSPI <= `ERROR_ADD_OUT_OF_RANGE;
			endcase
		end
		else if (WrEn) begin
			case (Add_SPI)
				8'h00:  Register0 <= Data_fromSPI;
				8'h01:  Register1 <= Data_fromSPI;
				8'h02:  Register2 <= Data_fromSPI;
				8'h03:  Register3 <= Data_fromSPI;
				8'h04:  Register4 <= Data_fromSPI;
				8'h05:  Register5 <= Data_fromSPI;
				8'h06:  Register6 <= Data_fromSPI;
				8'h07:  Register7 <= Data_fromSPI;
			endcase
		end
		//}}}

		//{{{ READ ACCESS 2
		case (Add2_in)
			8'h00: Data2_out <= Register0;
			8'h01: Data2_out <= Register1;
			8'h02: Data2_out <= Register2;
			8'h03: Data2_out <= Register3;
			8'h04: Data2_out <= Register4;
			8'h05: Data2_out <= Register5;
			8'h06: Data2_out <= Register6;
			8'h07: Data2_out <= Register7;
			default: Data2_out <= `ERROR_ADD_OUT_OF_RANGE;
		endcase
		//}}}

		//{{{ SPI INTERFACE
		// Two-stage synchroniser: captures async SPI inputs into Clk domain to prevent metastability
		SCK_metastable 	<= SCK;
		MOSI_metastable <= MOSI;
		SSEL_metastable <= SSEL;
		CPOL_metastable <= CPOL;
		CPHA_metastable <= CPHA;
		SCK_delay0 	<= SCK_metastable;
		MOSI_delay0 	<= MOSI_metastable;
		SSEL_delay0 	<= SSEL_metastable;
		CPOL_delay0 	<= CPOL_metastable;
		CPHA_delay0 	<= CPHA_metastable;
		SCK_delay1 	<= SCK_delay0;
		SSEL_delay1 	<= SSEL_delay0;

		WrEn 		<= 1'b0;

		case (SPI_State)

			`STATE_SPI_IDLE: begin
				BitCnt <= 0;
				// Mode pins are only taken over while idle so a transaction
				// always runs with a consistent CPOL/CPHA pair
				CPOL_latched <= CPOL_delay0;
				CPHA_latched <= CPHA_delay0;
				debug <= debug | 1;
				if (SSEL_delay0 == 0  && SSEL_delay1 == 1)
					SPI_State <= `STATE_SPI_COMMAND;
			end

			`STATE_SPI_COMMAND: begin
				debug <= debug | 8'h02;
				if (SampleEdge) begin
					ReceivedByte <= {ReceivedByte[6:0], MOSI_delay0};
					BitCnt <= BitCnt + 1;
				end
				if (BitCnt == 4'h8) begin
					BitCnt 	<= 4'h0;
					Add_SPI	<= {1'b0, ReceivedByte[6:0]};
					RnW 	<= ReceivedByte[7];
					if (ReceivedByte[7] == 1)
						SPI_State <= `STATE_SPI_READ;
					else
						SPI_State <= `STATE_SPI_WRITE;
				end
			end

			`STATE_SPI_WRITE: begin
				debug <= debug | 4;
				if (SampleEdge) begin
					ReceivedByte <= {ReceivedByte[6:0], MOSI_delay0};
					BitCnt <= BitCnt + 1;
				end
				if (BitCnt == 4'h8) begin
					WrEn <= 1;
					Data_fromSPI <= ReceivedByte;
					SPI_State <= `STATE_SPI_END;
				end
			end

			`STATE_SPI_READ: begin
				debug <= debug | 8;
				if (BitCnt == 0) begin
					if (DriveEdge) begin
						MISO <= Data_toSPI[7];
						DataToSend <= {Data_toSPI[6:0], 1'b0};
						BitCnt <= 1;
					end
				end
				else begin
					if (DriveEdge) begin
						MISO <= DataToSend[7];
						DataToSend <= {DataToSend[6:0], 1'b0};
						BitCnt <= BitCnt + 1;
					end
				end
				if (BitCnt == 4'h8) begin
					Data_fromSPI <= ReceivedByte;
					SPI_State <= `STATE_SPI_END;
				end
			end

			`STATE_SPI_END: begin
				debug <= debug | 16;
				if (SSEL_delay0)
					SPI_State <= `STATE_SPI_IDLE;
			end

		endcase
		//}}}

	end
end

endmodule

allmodes/tb_spi_slave_rpi.v
// Koen Van Caekenberghe (koen.vancaekenberghe@chipdesign.be), ChipDesign B.V., 08.2026
// Host verification test bench — Raspberry Pi SPI master model
//
// Models the BCM283x/BCM2711 hardware SPI controller as driven by spidev
// (spi.xfer2), which is how a Raspberry Pi talks to this slave:
//   - 100 MHz DUT system clock (10 ns period, as constrained in flow/constraint.sdc)
//   - 10 MHz SCK (100 ns period) — spi.max_speed_hz = 10_000_000
//   - CE0 (SSEL) asserted ~one SCK period before the first clock edge and
//     released ~half a period after the last one (spidev keeps CS asserted
//     for the whole xfer2 buffer)
//   - Bytes are clocked back-to-back with no inter-byte gap, MSB first
//   - All four modes (spi.mode = 0..3)
//
// Per mode, after a DUT reset:
//   Tx1: xfer2([0x81, 0x00])  READ  Register1        -> expect 0x0B
//   Tx2: xfer2([0x03, 0x5A])  WRITE 0x5A → Register3
//   Tx3: xfer2([0x83, 0x00])  READ  Register3 back   -> expect 0x5A
//   Tx4: xfer2([0xF5, 0x00])  READ  address 0x75     -> expect 0xFF (out of range)
//   Then checks the parallel read port and debug = 0x1F.
//
// Compile for RTL:
//   iverilog -g2012 -o tb_rpi_rtl.out tb_spi_slave_rpi.v && vvp tb_rpi_rtl.out
// Compile for synthesised netlist:
//   iverilog -g2012 -DSYNTH -o tb_rpi_syn.out flow/spi_slave_synth.v tb_spi_slave_rpi.v
//   vvp tb_rpi_syn.out

`timescale 1ns/1ns

`ifndef SYNTH
`include "spi_slave.v"
`endif

module tb_spi_slave_rpi();

// DUT system clock: 100 MHz
reg clk;
initial begin
    clk = 0;
    forever #5 clk = ~clk;
end

// SPI master timing: 10 MHz SCK
localparam SCK_HALF = 50;

reg [7:0] addr;
wire [7:0] data;
wire [7:0] debug;
wire miso;
reg mosi;
reg rst_n;
reg sck;
reg ssel;
reg cpol, cpha;

reg [7:0] rx0, rx1;   // received bytes of the current 2-byte xfer2
integer errors;
integer mode;

spi_slave spi_slave1(
    .Clk(clk),
    .iRST_N(rst_n),
    .CPOL(cpol),
    .CPHA(cpha),
    .SCK(sck),
    .MOSI(mosi),
    .SSEL(ssel),
    .MISO(miso),
    .Add2_in(addr),
    .Data2_out(data),
    .debug(debug)
);

// One byte on the wire, MSB first, in the currently selected mode.
task spi_clock_byte;
    input  [7:0] tx;
    output [7:0] rx;
    integer i;
    begin
        for (i = 7; i >= 0; i = i - 1) begin
            if (cpha == 0) begin
                mosi = tx[i];
                #(SCK_HALF) sck = ~cpol;   // leading edge: both sides sample
                rx[i] = miso;
                #(SCK_HALF) sck = cpol;    // trailing edge: shift
            end
            else begin
                sck = ~cpol;               // leading edge: both sides shift
                mosi = tx[i];
                #(SCK_HALF) sck = cpol;    // trailing edge: both sides sample
                rx[i] = miso;
                #(SCK_HALF);
            end
        end
    end
endtask

// spidev-style xfer2 of a 2-byte buffer: CS low for the whole buffer,
// bytes back-to-back, CS setup/hold of ~1 SCK period / ~0.5 SCK period.
task xfer2;
    input  [7:0] tx0;
    input  [7:0] tx1;
    begin
        ssel = 0;
        #(2*SCK_HALF);
        spi_clock_byte(tx0, rx0);
        spi_clock_byte(tx1, rx1);
        #(SCK_HALF);
        ssel = 1;
        #(2*SCK_HALF);   // inter-transfer gap
    end
endtask

task check_byte;
    input [8*40:1] label;
    input [7:0] got;
    input [7:0] expect_v;
    begin
        if (got !== expect_v) begin
            $display("FAIL mode %0d %0s: expected 0x%02X, got 0x%02X", mode, label, expect_v, got);
            errors = errors + 1;
        end
    end
endtask

task run_mode;
    input [1:0] m;
    begin
        cpol  = m[1];
        cpha  = m[0];
        addr  = 8'd3;
        mosi  = 0;
        ssel  = 1;
        rst_n = 0;
        sck   = m[1];
        #100 rst_n = 1;
        #100;

        xfer2(8'h81, 8'h00);              // READ Register1
        check_byte("Tx1 READ Reg1", rx1, 8'h0B);

        xfer2(8'h03, 8'h5A);              // WRITE 0x5A -> Register3
        #50;
        check_byte("Tx2 parallel Reg3", data, 8'h5A);

        xfer2(8'h83, 8'h00);              // READ Register3 back
        check_byte("Tx3 READ Reg3", rx1, 8'h5A);

        xfer2(8'hF5, 8'h00);              // READ address 0x75 (out of range)
        check_byte("Tx4 READ 0x75", rx1, 8'hFF);

        check_byte("debug", debug, 8'h1F);
        $display("MODE %0d (CPOL=%0d CPHA=%0d) %0t: rd1=0x%02X wr/rd3=0x%02X oor=0xFF? 0x%02X debug=0x%02X",
                 m, m[1], m[0], $time, 8'h0B, rx1 === 8'hFF ? 8'h5A : rx1, rx1, debug);
    end
endtask

initial begin
    errors = 0;
    for (mode = 0; mode <= 3; mode = mode + 1)
        run_mode(mode[1:0]);

    if (errors == 0)
        $display("PASS: Raspberry Pi master model — all checks passed in all 4 SPI modes");
    else
        $display("FAIL: %0d check(s) failed", errors);
    #100 $finish;
end

initial begin
`ifdef SYNTH
    $dumpfile("tb_spi_slave_rpi_synth.vcd");
`else
    $dumpfile("tb_spi_slave_rpi.vcd");
`endif
    $dumpvars(0, tb_spi_slave_rpi);
end

endmodule

allmodes/tb_spi_slave_rpi.vcd
$date
	Sat Aug  8 21:53:38 2026
$end
$version
	Icarus Verilog
$end
$timescale
	1ns
$end
$scope module tb_spi_slave_rpi $end
$var wire 1 ! miso $end
$var wire 8 " debug [7:0] $end
$var wire 8 # data [7:0] $end
$var parameter 32 $ SCK_HALF $end
$var reg 8 % addr [7:0] $end
$var reg 1 & clk $end
$var reg 1 ' cpha $end
$var reg 1 ( cpol $end
$var reg 1 ) mosi $end
$var reg 1 * rst_n $end
$var reg 8 + rx0 [7:0] $end
$var reg 8 , rx1 [7:0] $end
$var reg 1 - sck $end
$var reg 1 . ssel $end
$var integer 32 / errors [31:0] $end
$var integer 32 0 mode [31:0] $end
$scope module spi_slave1 $end
$var wire 8 1 Add2_in [7:0] $end
$var wire 1 ' CPHA $end
$var wire 1 ( CPOL $end
$var wire 1 & Clk $end
$var wire 1 2 LeadingEdge $end
$var wire 1 ) MOSI $end
$var wire 1 - SCK $end
$var wire 1 3 SCK_norm0 $end
$var wire 1 4 SCK_norm1 $end
$var wire 1 . SSEL $end
$var wire 1 5 TrailingEdge $end
$var wire 1 * iRST_N $end
$var wire 1 6 SampleEdge $end
$var wire 1 7 DriveEdge $end
$var reg 8 8 Add_SPI [7:0] $end
$var reg 4 9 BitCnt [3:0] $end
$var reg 1 : CPHA_delay0 $end
$var reg 1 ; CPHA_latched $end
$var reg 1 < CPHA_metastable $end
$var reg 1 = CPOL_delay0 $end
$var reg 1 > CPOL_latched $end
$var reg 1 ? CPOL_metastable $end
$var reg 8 @ Data2_out [7:0] $end
$var reg 8 A DataToSend [7:0] $end
$var reg 8 B Data_fromSPI [7:0] $end
$var reg 8 C Data_toSPI [7:0] $end
$var reg 1 ! MISO $end
$var reg 1 D MOSI_delay0 $end
$var reg 1 E MOSI_metastable $end
$var reg 8 F ReceivedByte [7:0] $end
$var reg 8 G Register0 [7:0] $end
$var reg 8 H Register1 [7:0] $end
$var reg 8 I Register2 [7:0] $end
$var reg 8 J Register3 [7:0] $end
$var reg 8 K Register4 [7:0] $end
$var reg 8 L Register5 [7:0] $end
$var reg 8 M Register6 [7:0] $end
$var reg 8 N Register7 [7:0] $end
$var reg 1 O RnW $end
$var reg 1 P SCK_delay0 $end
$var reg 1 Q SCK_delay1 $end
$var reg 1 R SCK_metastable $end
$var reg 3 S SPI_State [2:0] $end
$var reg 1 T SSEL_delay0 $end
$var reg 1 U SSEL_delay1 $end
$var reg 1 V SSEL_metastable $end
$var reg 1 W WrEn $end
$var reg 8 X debug [7:0] $end
$upscope $end
$scope task check_byte $end
$var reg 8 Y expect_v [7:0] $end
$var reg 8 Z got [7:0] $end
$var reg 320 [ label [320:1] $end
$upscope $end
$scope task run_mode $end
$var reg 2 \ m [1:0] $end
$upscope $end
$scope task spi_clock_byte $end
$var reg 8 ] rx [7:0] $end
$var reg 8 ^ tx [7:0] $end
$var integer 32 _ i [31:0] $end
$upscope $end
$scope task xfer2 $end
$var reg 8 ` tx0 [7:0] $end
$var reg 8 a tx1 [7:0] $end
$upscope $end
$upscope $end
$enddefinitions $end
$comment Show the parameter values. $end
$dumpall
b110010 $
$end
#0
$dumpvars
bx a
bx `
bx _
bx ^
bx ]
b0 \
bx [
bx Z
bx Y
b0 X
0W
0V
0U
0T
b0 S
0R
0Q
0P
0O
b110000 N
b100000 M
b10000 L
b1110 K
b1101 J
b1100 I
b1011 H
b1010 G
b0 F
0E
0D
b0 C
b0 B
b0 A
b0 @
0?
0>
0=
0<
0;
0:
b0 9
b0 8
07
06
05
04
03
02
b11 1
b0 0
b0 /
1.
0-
bx ,
bx +
0*
0)
0(
0'
0&
b11 %
b0 #
b0 "
0!
$end
#5
1&
#10
0&
#15
1&
#20
0&
#25
1&
#30
0&
#35
1&
#40
0&
#45
1&
#50
0&
#55
1&
#60
0&
#65
1&
#70
0&
#75
1&
#80
0&
#85
1&
#90
0&
#95
1&
#100
0&
1*
#105
b1 "
b1 X
1V
b1101 #
b1101 @
1&
#110
0&
#115
1T
1&
#120
0&
#125
1U
1&
#130
0&
#135
1&
#140
0&
#145
1&
#150
0&
#155
1&
#160
0&
#165
1&
#170
0&
#175
1&
#180
0&
#185
1&
#190
0&
#195
1&
#200
0&
0.
b0 a
b10000001 `
#205
0V
1&
#210
0&
#215
0T
1&
#220
0&
#225
b1 S
0U
1&
#230
0&
#235
b11 "
b11 X
1&
#240
0&
#245
1&
#250
0&
#255
1&
#260
0&
#265
1&
#270
0&
#275
1&
#280
0&
#285
1&
#290
0&
#295
1&
#300
0&
1)
b111 _
b10000001 ^
#305
1E
1&
#310
0&
#315
1D
1&
#320
0&
#325
1&
#330
0&
#335
1&
#340
0&
#345
1&
#350
0&
b0xxxxxxx ]
1-
#355
1R
1&
#360
0&
#365
16
12
13
1P
1&
#370
0&
#375
06
02
14
b1 9
b1 F
1Q
1&
#380
0&
#385
1&
#390
0&
#395
1&
#400
0&
0)
b110 _
0-
#405
0E
0R
1&
#410
0&
#415
17
15
03
0D
0P
1&
#420
0&
#425
07
05
04
0Q
1&
#430
0&
#435
1&
#440
0&
#445
1&
#450
0&
b0xxxxxx ]
1-
#455
1R
1&
#460
0&
#465
16
12
13
1P
1&
#470
0&
#475
06
02
14
b10 9
b10 F
1Q
1&
#480
0&
#485
1&
#490
0&
#495
1&
#500
0&
b101 _
0-
#505
0R
1&
#510
0&
#515
17
15
03
0P
1&
#520
0&
#525
07
05
04
0Q
1&
#530
0&
#535
1&
#540
0&
#545
1&
#550
0&
b0xxxxx ]
1-
#555
1R
1&
#560
0&
#565
16
12
13
1P
1&
#570
0&
#575
06
02
14
b11 9
b100 F
1Q
1&
#580
0&
#585
1&
#590
0&
#595
1&
#600
0&
b100 _
0-
#605
0R
1&
#610
0&
#615
17
15
03
0P
1&
#620
0&
#625
07
05
04
0Q
1&
#630
0&
#635
1&
#640
0&
#645
1&
#650
0&
b0xxxx ]
1-
#655
1R
1&
#660
0&
#665
16
12
13
1P
1&
#670
0&
#675
06
02
14
b100 9
b1000 F
1Q
1&
#680
0&
#685
1&
#690
0&
#695
1&
#700
0&
b11 _
0-
#705
0R
1&
#710
0&
#715
17
15
03
0P
1&
#720
0&
#725
07
05
04
0Q
1&
#730
0&
#735
1&
#740
0&
#745
1&
#750
0&
b0xxx ]
1-
#755
1R
1&
#760
0&
#765
16
12
13
1P
1&
#770
0&
#775
06
02
14
b101 9
b10000 F
1Q
1&
#780
0&
#785
1&
#790
0&
#795
1&
#800
0&
b10 _
0-
#805
0R
1&
#810
0&
#815
17
15
03
0P
1&
#820
0&
#825
07
05
04
0Q
1&
#830
0&
#835
1&
#840
0&
#845
1&
#850
0&
b0xx ]
1-
#855
1R
1&
#860
0&
#865
16
12
13
1P
1&
#870
0&
#875
06
02
14
b110 9
b100000 F
1Q
1&
#880
0&
#885
1&
#890
0&
#895
1&
#900
0&
b1 _
0-
#905
0R
1&
#910
0&
#915
17
15
03
0P
1&
#920
0&
#925
07
05
04
0Q
1&
#930
0&
#935
1&
#940
0&
#945
1&
#950
0&
b0x ]
1-
#955
1R
1&
#960
0&
#965
16
12
13
1P
1&
#970
0&
#975
06
02
14
b111 9
b1000000 F
1Q
1&
#980
0&
#985
1&
#990
0&
#995
1&
#1000
0&
1)
b0 _
0-
#1005
1E
0R
1&
#1010
0&
#1015
17
15
03
1D
0P
1&
#1020
0&
#1025
07
05
04
0Q
1&
#1030
0&
#1035
1&
#1040
0&
#1045
1&
#1050
0&
b0 ]
1-
#1055
1R
1&
#1060
0&
#1065
16
12
13
1P
1&
#1070
0&
#1075
06
02
14
b1000 9
b10000001 F
1Q
1&
#1080
0&
#1085
b11 S
1O
b1 8
b0 9
1&
#1090
0&
#1095
b1011 "
b1011 X
b1011 C
1&
#1100
0&
0)
b0 ^
b0 +
b111 _
0-
#1105
0E
0R
1&
#1110
0&
#1115
17
15
03
0D
0P
1&
#1120
0&
#1125
07
05
04
b1 9
b10110 A
0Q
1&
#1130
0&
#1135
1&
#1140
0&
#1145
1&
#1150
0&
1-
#1155
1R
1&
#1160
0&
#1165
16
12
13
1P
1&
#1170
0&
#1175
06
02
14
1Q
1&
#1180
0&
#1185
1&
#1190
0&
#1195
1&
#1200
0&
b110 _
0-
#1205
0R
1&
#1210
0&
#1215
17
15
03
0P
1&
#1220
0&
#1225
07
05
04
b10 9
b101100 A
0Q
1&
#1230
0&
#1235
1&
#1240
0&
#1245
1&
#1250
0&
1-
#1255
1R
1&
#1260
0&
#1265
16
12
13
1P
1&
#1270
0&
#1275
06
02
14
1Q
1&
#1280
0&
#1285
1&
#1290
0&
#1295
1&
#1300
0&
b101 _
0-
#1305
0R
1&
#1310
0&
#1315
17
15
03
0P
1&
#1320
0&
#1325
07
05
04
b11 9
b1011000 A
0Q
1&
#1330
0&
#1335
1&
#1340
0&
#1345
1&
#1350
0&
1-
#1355
1R
1&
#1360
0&
#1365
16
12
13
1P
1&
#1370
0&
#1375
06
02
14
1Q
1&
#1380
0&
#1385
1&
#1390
0&
#1395
1&
#1400
0&
b100 _
0-
#1405
0R
1&
#1410
0&
#1415
17
15
03
0P
1&
#1420
0&
#1425
07
05
04
b100 9
b10110000 A
0Q
1&
#1430
0&
#1435
1&
#1440
0&
#1445
1&
#1450
0&
1-
#1455
1R
1&
#1460
0&
#1465
16
12
13
1P
1&
#1470
0&
#1475
06
02
14
1Q
1&
#1480
0&
#1485
1&
#1490
0&
#1495
1&
#1500
0&
b11 _
0-
#1505
0R
1&
#1510
0&
#1515
17
15
03
0P
1&
#1520
0&
#1525
07
05
04
b101 9
b1100000 A
1!
0Q
1&
#1530
0&
#1535
1&
#1540
0&
#1545
1&
#1550
0&
b1000 ]
1-
#1555
1R
1&
#1560
0&
#1565
16
12
13
1P
1&
#1570
0&
#1575
06
02
14
1Q
1&
#1580
0&
#1585
1&
#1590
0&
#1595
1&
#1600
0&
b10 _
0-
#1605
0R
1&
#1610
0&
#1615
17
15
03
0P
1&
#1620
0&
#1625
07
05
04
b110 9
b11000000 A
0!
0Q
1&
#1630
0&
#1635
1&
#1640
0&
#1645
1&
#1650
0&
1-
#1655
1R
1&
#1660
0&
#1665
16
12
13
1P
1&
#1670
0&
#1675
06
02
14
1Q
1&
#1680
0&
#1685
1&
#1690
0&
#1695
1&
#1700
0&
b1 _
0-
#1705
0R
1&
#1710
0&
#1715
17
15
03
0P
1&
#1720
0&
#1725
07
05
04
b111 9
b10000000 A
1!
0Q
1&
#1730
0&
#1735
1&
#1740
0&
#1745
1&
#1750
0&
b1010 ]
1-
#1755
1R
1&
#1760
0&
#1765
16
12
13
1P
1&
#1770
0&
#1775
06
02
14
1Q
1&
#1780
0&
#1785
1&
#1790
0&
#1795
1&
#1800
0&
b0 _
0-
#1805
0R
1&
#1810
0&
#1815
17
15
03
0P
1&
#1820
0&
#1825
07
05
04
b1000 9
b0 A
0Q
1&
#1830
0&
#1835
b100 S
b10000001 B
1&
#1840
0&
#1845
b11011 "
b11011 X
1&
#1850
0&
b1011 ]
1-
#1855
1R
1&
#1860
0&
#1865
16
12
13
1P
1&
#1870
0&
#1875
06
02
14
1Q
1&
#1880
0&
#1885
1&
#1890
0&
#1895
1&
#1900
0&
b1011 ,
b11111111111111111111111111111111 _
0-
#1905
0R
1&
#1910
0&
#1915
17
15
03
0P
1&
#1920
0&
#1925
07
05
04
0Q
1&
#1930
0&
#1935
1&
#1940
0&
#1945
1&
#1950
0&
1.
#1955
1V
1&
#1960
0&
#1965
1T
1&
#1970
0&
#1975
b0 S
1U
1&
#1980
0&
#1985
b0 9
1&
#1990
0&
#1995
1&
#2000
0&
#2005
1&
#2010
0&
#2015
1&
#2020
0&
#2025
1&
#2030
0&
#2035
1&
#2040
0&
#2045
1&
#2050
0&
0.
b1011010 a
b11 `
b1011 Y
b1011 Z
b1010100011110000011000100100000010100100100010101000001010001000010000001010010011001010110011100110001 [
#2055
0V
1&
#2060
0&
#2065
0T
1&
#2070
0&
#2075
b1 S
0U
1&
#2080
0&
#2085
1&
#2090
0&
#2095
1&
#2100
0&
#2105
1&
#2110
0&
#2115
1&
#2120
0&
#2125
1&
#2130
0&
#2135
1&
#2140
0&
#2145
1&
#2150
0&
b111 _
b11 ^
#2155
1&
#2160
0&
#2165
1&
#2170
0&
#2175
1&
#2180
0&
#2185
1&
#2190
0&
#2195
1&
#2200
0&
b10001011 ]
1-
#2205
1R
1&
#2210
0&
#2215
16
12
13
1P
1&
#2220
0&
#2225
06
02
14
b1 9
b10 F
1Q
1&
#2230
0&
#2235
1&
#2240
0&
#2245
1&
#2250
0&
b110 _
0-
#2255
0R
1&
#2260
0&
#2265
17
15
03
0P
1&
#2270
0&
#2275
07
05
04
0Q
1&
#2280
0&
#2285
1&
#2290
0&
#2295
1&
#2300
0&
b11001011 ]
1-
#2305
1R
1&
#2310
0&
#2315
16
12
13
1P
1&
#2320
0&
#2325
06
02
14
b10 9
b100 F
1Q
1&
#2330
0&
#2335
1&
#2340
0&
#2345
1&
#2350
0&
b101 _
0-
#2355
0R
1&
#2360
0&
#2365
17
15
03
0P
1&
#2370
0&
#2375
07
05
04
0Q
1&
#2380
0&
#2385
1&
#2390
0&
#2395
1&
#2400
0&
b11101011 ]
1-
#2405
1R
1&
#2410
0&
#2415
16
12
13
1P
1&
#2420
0&
#2425
06
02
14
b11 9
b1000 F
1Q
1&
#2430
0&
#2435
1&
#2440
0&
#2445
1&
#2450
0&
b100 _
0-
#2455
0R
1&
#2460
0&
#2465
17
15
03
0P
1&
#2470
0&
#2475
07
05
04
0Q
1&
#2480
0&
#2485
1&
#2490
0&
#2495
1&
#2500
0&
b11111011 ]
1-
#2505
1R
1&
#2510
0&
#2515
16
12
13
1P
1&
#2520
0&
#2525
06
02
14
b100 9
b10000 F
1Q
1&
#2530
0&
#2535
1&
#2540
0&
#2545
1&
#2550
0&
b11 _
0-
#2555
0R
1&
#2560
0&
#2565
17
15
03
0P
1&
#2570
0&
#2575
07
05
04
0Q
1&
#2580
0&
#2585
1&
#2590
0&
#2595
1&
#2600
0&
1-
#2605
1R
1&
#2610
0&
#2615
16
12
13
1P
1&
#2620
0&
#2625
06
02
14
b101 9
b100000 F
1Q
1&
#2630
0&
#2635
1&
#2640
0&
#2645
1&
#2650
0&
b10 _
0-
#2655
0R
1&
#2660
0&
#2665
17
15
03
0P
1&
#2670
0&
#2675
07
05
04
0Q
1&
#2680
0&
#2685
1&
#2690
0&
#2695
1&
#2700
0&
b11111111 ]
1-
#2705
1R
1&
#2710
0&
#2715
16
12
13
1P
1&
#2720
0&
#2725
06
02
14
b110 9
b1000000 F
1Q
1&
#2730
0&
#2735
1&
#2740
0&
#2745
1&
#2750
0&
1)
b1 _
0-
#2755
1E
0R
1&
#2760
0&
#2765
17
15
03
1D
0P
1&
#2770
0&
#2775
07
05
04
0Q
1&
#2780
0&
#2785
1&
#2790
0&
#2795
1&
#2800
0&
1-
#2805
1R
1&
#2810
0&
#2815
16
12
13
1P
1&
#2820
0&
#2825
06
02
14
b111 9
b10000001 F
1Q
1&
#2830
0&
#2835
1&
#2840
0&
#2845
1&
#2850
0&
b0 _
0-
#2855
0R
1&
#2860
0&
#2865
17
15
03
0P
1&
#2870
0&
#2875
07
05
04
0Q
1&
#2880
0&
#2885
1&
#2890
0&
#2895
1&
#2900
0&
1-
#2905
1R
1&
#2910
0&
#2915
16
12
13
1P
1&
#2920
0&
#2925
06
02
14
b1000 9
b11 F
1Q
1&
#2930
0&
#2935
b10 S
0O
b11 8
b0 9
1&
#2940
0&
#2945
b11111 "
b11111 X
1&
#2950
0&
0)
b1011010 ^
b11111111 +
b111 _
0-
#2955
0E
0R
1&
#2960
0&
#2965
17
15
03
0D
0P
1&
#2970
0&
#2975
07
05
04
0Q
1&
#2980
0&
#2985
1&
#2990
0&
#2995
1&
#3000
0&
1-
#3005
1R
1&
#3010
0&
#3015
16
12
13
1P
1&
#3020
0&
#3025
06
02
14
b1 9
b110 F
1Q
1&
#3030
0&
#3035
1&
#3040
0&
#3045
1&
#3050
0&
1)
b110 _
0-
#3055
1E
0R
1&
#3060
0&
#3065
17
15
03
1D
0P
1&
#3070
0&
#3075
07
05
04
0Q
1&
#3080
0&
#3085
1&
#3090
0&
#3095
1&
#3100
0&
1-
#3105
1R
1&
#3110
0&
#3115
16
12
13
1P
1&
#3120
0&
#3125
06
02
14
b10 9
b1101 F
1Q
1&
#3130
0&
#3135
1&
#3140
0&
#3145
1&
#3150
0&
0)
b101 _
0-
#3155
0E
0R
1&
#3160
0&
#3165
17
15
03
0D
0P
1&
#3170
0&
#3175
07
05
04
0Q
1&
#3180
0&
#3185
1&
#3190
0&
#3195
1&
#3200
0&
1-
#3205
1R
1&
#3210
0&
#3215
16
12
13
1P
1&
#3220
0&
#3225
06
02
14
b11 9
b11010 F
1Q
1&
#3230
0&
