allmodes/spi_slave.v
// Koen Van Caekenberghe (koen.vancaekenberghe@chipdesign.be), ChipDesign B.V., 06.2026
// SPI Slave — all-modes variant
//
// - SPI mode: 0, 1, 2 or 3, selected by the CPOL / CPHA input pins
//     CPOL = SCK idle level, CPHA = 0: sample on leading edge / drive on trailing edge
//                            CPHA = 1: drive on leading edge / sample on trailing edge
//   CPOL/CPHA are strap or GPIO-driven configuration inputs; they are captured
//   while the FSM is in IDLE, so they must be stable before SSEL is asserted.
// - Address byte: MSB is R/nW command bit (1=Read, 0=Write); lower 7 bits are register address (0x00–0x7F)
// - Register map: 8 × 8-bit registers at addresses 0x00–0x07; reads outside this range return 0xFF
// - Register width: 1 byte
// - Secondary parallel read port (Add2_in / Data2_out) allows concurrent register readback independent of SPI
// - SCK is oversampled by Clk (two-flip-flop synchroniser + edge detection):
//   keep SCK ≤ Clk/8 (e.g. 12.5 MHz SCK at 100 MHz Clk)

`define STATE_SPI_IDLE 		3'd0
`define STATE_SPI_COMMAND	3'd1
`define STATE_SPI_WRITE 	3'd2
`define STATE_SPI_READ 		3'd3
`define STATE_SPI_END 		3'd4

`define ERROR_ADD_OUT_OF_RANGE 	8'hFF

module spi_slave
(
	input Clk,          // system clock; all internal logic is synchronous to this
	input iRST_N,       // active-low asynchronous reset

	input CPOL,         // SPI mode select: SCK idle level (mode[1])
	input CPHA,         // SPI mode select: sample/drive edge choice (mode[0])

	input SCK,          // SPI clock from master
	input MOSI,         // master-out slave-in data
	input SSEL,         // SPI slave select, active low
	output reg MISO,    // master-in slave-out data

	input [7:0] Add2_in,        // parallel read port: register address
	output reg [7:0] Data2_out, // parallel read port: register data out (updated every Clk cycle)

	output reg [7:0] debug      // sticky OR of state-machine states visited since last reset
);

reg [7:0] Register0, Register1, Register2, Register3, Register4, Register5, Register6, Register7;

reg SCK_metastable, MOSI_metastable, SSEL_metastable, CPOL_metastable, CPHA_metastable;
reg SCK_delay0, MOSI_delay0, SSEL_delay0, CPOL_delay0, CPHA_delay0;
reg SCK_delay1, SSEL_delay1;
reg CPOL_latched, CPHA_latched;
reg WrEn, RnW;
reg [3:0] BitCnt;
reg [7:0] ReceivedByte, Data_fromSPI, DataToSend, Data_toSPI, Add_SPI;
reg [2:0] SPI_State;

// SCK normalised to look like mode-0 polarity: idle low, leading edge = rising
wire SCK_norm0 = SCK_delay0 ^ CPOL_latched;
wire SCK_norm1 = SCK_delay1 ^ CPOL_latched;
wire LeadingEdge  =  SCK_norm0 & ~SCK_norm1;
wire TrailingEdge = ~SCK_norm0 &  SCK_norm1;
wire SampleEdge = CPHA_latched ? TrailingEdge : LeadingEdge;  // master has data valid here
wire DriveEdge  = CPHA_latched ? LeadingEdge  : TrailingEdge; // slave updates MISO here

always @(posedge Clk or negedge iRST_N) begin
	if(!iRST_N) begin
		Register0	<= 8'h0A;
		Register1	<= 8'h0B;
		Register2	<= 8'h0C;
		Register3	<= 8'h0D;
		Register4	<= 8'h0E;
		Register5	<= 8'h10;
		Register6	<= 8'h20;
		Register7	<= 8'h30;
		Data_toSPI 	<= 8'h00;
		Data2_out	<= 8'h00;

		SCK_metastable 	<= 1'b0;
		MOSI_metastable <= 1'b0;
		SSEL_metastable <= 1'b0;
		CPOL_metastable <= 1'b0;
		CPHA_metastable <= 1'b0;
		SCK_delay0 	<= 1'b0;
		MOSI_delay0 	<= 1'b0;
		SSEL_delay0 	<= 1'b0;
		CPOL_delay0 	<= 1'b0;
		CPHA_delay0 	<= 1'b0;
		SCK_delay1 	<= 1'b0;
		SSEL_delay1 	<= 1'b0;
		CPOL_latched	<= 1'b0;
		CPHA_latched	<= 1'b0;
		WrEn 		<= 1'b0;
		RnW		<= 1'b0;
		BitCnt		<= 4'h0;
		ReceivedByte	<= 8'h00;
		Data_fromSPI	<= 8'h00;
		DataToSend	<= 8'h00;
		Add_SPI		<= 8'h00;

		MISO		<= 1'b0;

		debug		<= 1'b0;

		SPI_State 	<= `STATE_SPI_IDLE;
	end
	else begin

		//{{{ READ/WRITE ACCESS
		if (RnW) begin
			case (Add_SPI)
				8'h00: Data_toSPI <= Register0;
				8'h01: Data_toSPI <= Register1;
				8'h02: Data_toSPI <= Register2;
				8'h03: Data_toSPI <= Register3;
				8'h04: Data_toSPI <= Register4;
				8'h05: Data_toSPI <= Register5;
				8'h06: Data_toSPI <= Register6;
				8'h07: Data_toSPI <= Register7;
				default: Data_toSPI <= `ERROR_ADD_OUT_OF_RANGE;
			endcase
		end
		else if (WrEn) begin
			case (Add_SPI)
				8'h00:  Register0 <= Data_fromSPI;
				8'h01:  Register1 <= Data_fromSPI;
				8'h02:  Register2 <= Data_fromSPI;
				8'h03:  Register3 <= Data_fromSPI;
				8'h04:  Register4 <= Data_fromSPI;
				8'h05:  Register5 <= Data_fromSPI;
				8'h06:  Register6 <= Data_fromSPI;
				8'h07:  Register7 <= Data_fromSPI;
			endcase
		end
		//}}}

		//{{{ READ ACCESS 2
		case (Add2_in)
			8'h00: Data2_out <= Register0;
			8'h01: Data2_out <= Register1;
			8'h02: Data2_out <= Register2;
			8'h03: Data2_out <= Register3;
			8'h04: Data2_out <= Register4;
			8'h05: Data2_out <= Register5;
			8'h06: Data2_out <= Register6;
			8'h07: Data2_out <= Register7;
			default: Data2_out <= `ERROR_ADD_OUT_OF_RANGE;
		endcase
		//}}}

		//{{{ SPI INTERFACE
		// Two-stage synchroniser: captures async SPI inputs into Clk domain to prevent metastability
		SCK_metastable 	<= SCK;
		MOSI_metastable <= MOSI;
		SSEL_metastable <= SSEL;
		CPOL_metastable <= CPOL;
		CPHA_metastable <= CPHA;
		SCK_delay0 	<= SCK_metastable;
		MOSI_delay0 	<= MOSI_metastable;
		SSEL_delay0 	<= SSEL_metastable;
		CPOL_delay0 	<= CPOL_metastable;
		CPHA_delay0 	<= CPHA_metastable;
		SCK_delay1 	<= SCK_delay0;
		SSEL_delay1 	<= SSEL_delay0;

		WrEn 		<= 1'b0;

		case (SPI_State)

			`STATE_SPI_IDLE: begin
				BitCnt <= 0;
				// Mode pins are only taken over while idle so a transaction
				// always runs with a consistent CPOL/CPHA pair
				CPOL_latched <= CPOL_delay0;
				CPHA_latched <= CPHA_delay0;
				debug <= debug | 1;
				if (SSEL_delay0 == 0  && SSEL_delay1 == 1)
					SPI_State <= `STATE_SPI_COMMAND;
			end

			`STATE_SPI_COMMAND: begin
				debug <= debug | 8'h02;
				if (SampleEdge) begin
					ReceivedByte <= {ReceivedByte[6:0], MOSI_delay0};
					BitCnt <= BitCnt + 1;
				end
				if (BitCnt == 4'h8) begin
					BitCnt 	<= 4'h0;
					Add_SPI	<= {1'b0, ReceivedByte[6:0]};
					RnW 	<= ReceivedByte[7];
					if (ReceivedByte[7] == 1)
						SPI_State <= `STATE_SPI_READ;
					else
						SPI_State <= `STATE_SPI_WRITE;
				end
			end

			`STATE_SPI_WRITE: begin
				debug <= debug | 4;
				if (SampleEdge) begin
					ReceivedByte <= {ReceivedByte[6:0], MOSI_delay0};
					BitCnt <= BitCnt + 1;
				end
				if (BitCnt == 4'h8) begin
					WrEn <= 1;
					Data_fromSPI <= ReceivedByte;
					SPI_State <= `STATE_SPI_END;
				end
			end

			`STATE_SPI_READ: begin
				debug <= debug | 8;
				if (BitCnt == 0) begin
					if (DriveEdge) begin
						MISO <= Data_toSPI[7];
						DataToSend <= {Data_toSPI[6:0], 1'b0};
						BitCnt <= 1;
					end
				end
				else begin
					if (DriveEdge) begin
						MISO <= DataToSend[7];
						DataToSend <= {DataToSend[6:0], 1'b0};
						BitCnt <= BitCnt + 1;
					end
				end
				if (BitCnt == 4'h8) begin
					Data_fromSPI <= ReceivedByte;
					SPI_State <= `STATE_SPI_END;
				end
			end

			`STATE_SPI_END: begin
				debug <= debug | 16;
				if (SSEL_delay0)
					SPI_State <= `STATE_SPI_IDLE;
			end

		endcase
		//}}}

	end
end

endmodule

allmodes/tb_spi_slave.v
// Koen Van Caekenberghe (koen.vancaekenberghe@chipdesign.be), ChipDesign B.V., 08.2026
// Test bench for SPI Slave — all-modes variant
//
// Runs the same three transactions in each of the four SPI modes
// (mode = {CPOL,CPHA} = 0,1,2,3), with a DUT reset between modes:
//   Tx1: READ  Register1 (addr 0x01) — verifies reset value 0x0B on MISO
//   Tx2: WRITE (0xA0|mode) → Register3 (addr 0x03)
//   Tx3: READ  Register3 (addr 0x03) — confirms Tx2 write on MISO
// After each mode the debug port must read 0x1F (all five FSM states visited).
//
// Master model timing (20 ns SCK period, 500 ns system clock = 2 ns period):
//   CPHA=0: MOSI is set up half a period before the leading edge; MISO is
//           sampled at the leading edge (the DUT drove it on the previous
//           trailing edge).
//   CPHA=1: MOSI changes on the leading edge; MISO is sampled at the
//           trailing edge (the DUT drove it on the preceding leading edge).
//
// Compile for RTL:
//   iverilog -g2012 -o tb_rtl.out tb_spi_slave.v && vvp tb_rtl.out
// Compile for synthesised netlist:
//   iverilog -g2012 -DSYNTH -o tb_syn.out flow/spi_slave_synth.v tb_spi_slave.v
//   vvp tb_syn.out

`timescale 1ns/1ns

`ifndef SYNTH
`include "spi_slave.v"
`endif

module tb_spi_slave();

reg [7:0] addr;
reg clk;
initial begin
    clk = 0;
    forever #1 clk = ~clk;
end

wire [7:0] data;
wire [7:0] debug;
wire miso;
reg mosi;
reg rst_n;
reg sck;
reg ssel;
reg cpol, cpha;

reg [7:0] rx_cmd;    // MISO during command byte (ignored)
reg [7:0] miso_rx1;  // MISO byte captured during Tx1 READ
reg [7:0] miso_rx3;  // MISO byte captured during Tx3 READ
integer errors;
integer mode;

spi_slave spi_slave1(
    .Clk(clk),
    .iRST_N(rst_n),
    .CPOL(cpol),
    .CPHA(cpha),
    .SCK(sck),
    .MOSI(mosi),
    .SSEL(ssel),
    .MISO(miso),
    .Add2_in(addr),
    .Data2_out(data),
    .debug(debug)
);

// Transfer one byte MSB-first in the currently selected mode.
// tx goes out on MOSI, the byte seen on MISO is returned in rx.
task spi_xfer_byte;
    input  [7:0] tx;
    output [7:0] rx;
    integer i;
    begin
        for (i = 7; i >= 0; i = i - 1) begin
            if (cpha == 0) begin
                mosi = tx[i];
                #10 sck = ~cpol;    // leading edge: both sides sample
                rx[i] = miso;
                #10 sck = cpol;     // trailing edge: slave drives next bit
            end
            else begin
                sck = ~cpol;        // leading edge: both sides drive
                mosi = tx[i];
                #10 sck = cpol;     // trailing edge: both sides sample
                rx[i] = miso;
                #10;
            end
        end
    end
endtask

// Run the Tx1/Tx2/Tx3 sequence in SPI mode m and check the results.
task run_mode;
    input [1:0] m;
    begin
        cpol  = m[1];
        cpha  = m[0];
        addr  = 8'd3;      // parallel port points at Register3 throughout
        mosi  = 0;
        ssel  = 1;
        rst_n = 0;
        sck   = m[1];      // SCK idles at CPOL
        #20 rst_n = 1;
        #20;

        // --- Tx1: READ Register1 (addr_byte=0x81: RnW=1, addr=0x01) ---
        ssel = 0; #10;
        spi_xfer_byte(8'h81, rx_cmd);
        spi_xfer_byte(8'h00, miso_rx1);
        #10 ssel = 1;
        #20;

        // --- Tx2: WRITE (0xA0|mode) → Register3 (addr_byte=0x03) ---
        ssel = 0; #10;
        spi_xfer_byte(8'h03, rx_cmd);
        spi_xfer_byte(8'hA0 | m, rx_cmd);
        #10 ssel = 1;
        #20;

        // --- Tx3: READ Register3 (addr_byte=0x83: RnW=1, addr=0x03) ---
        ssel = 0; #10;
        spi_xfer_byte(8'h83, rx_cmd);
        spi_xfer_byte(8'h00, miso_rx3);
        #10 ssel = 1;
        #20;

        if (miso_rx1 !== 8'h0B) begin
            $display("FAIL mode %0d Tx1 READ Reg1 : expected miso=0x0B, got 0x%02X", m, miso_rx1);
            errors = errors + 1;
        end
        if (data !== (8'hA0 | m)) begin
            $display("FAIL mode %0d parallel Reg3: expected data=0x%02X, got 0x%02X", m, 8'hA0 | m, data);
            errors = errors + 1;
        end
        if (miso_rx3 !== (8'hA0 | m)) begin
            $display("FAIL mode %0d Tx3 READ Reg3: expected miso=0x%02X, got 0x%02X", m, 8'hA0 | m, miso_rx3);
            errors = errors + 1;
        end
        if (debug !== 8'h1F) begin
            $display("FAIL mode %0d debug        : expected 0x1F, got 0x%02X", m, debug);
            errors = errors + 1;
        end
        $display("MODE %0d (CPOL=%0d CPHA=%0d) %0t: miso_rx1=0x%02X data=0x%02X miso_rx3=0x%02X debug=0x%02X",
                 m, m[1], m[0], $time, miso_rx1, data, miso_rx3, debug);
    end
endtask

initial begin
    errors = 0;
    for (mode = 0; mode <= 3; mode = mode + 1)
        run_mode(mode[1:0]);

    if (errors == 0)
        $display("PASS: all checks passed in all 4 SPI modes");
    else
        $display("FAIL: %0d check(s) failed", errors);
    #20 $finish;
end

initial begin
`ifdef SYNTH
    $dumpfile("tb_spi_slave_synth.vcd");
`else
    $dumpfile("tb_spi_slave.vcd");
`endif
    $dumpvars(0, tb_spi_slave);
end

endmodule

allmodes/tb_spi_slave.vcd
$date
	Sat Aug  8 17:39:31 2026
$end
$version
	Icarus Verilog
$end
$timescale
	1ns
$end
$scope module tb_spi_slave $end
$var wire 1 ! miso $end
$var wire 8 " debug [7:0] $end
$var wire 8 # data [7:0] $end
$var reg 8 $ addr [7:0] $end
$var reg 1 % clk $end
$var reg 1 & cpha $end
$var reg 1 ' cpol $end
$var reg 8 ( miso_rx1 [7:0] $end
$var reg 8 ) miso_rx3 [7:0] $end
$var reg 1 * mosi $end
$var reg 1 + rst_n $end
$var reg 8 , rx_cmd [7:0] $end
$var reg 1 - sck $end
$var reg 1 . ssel $end
$var integer 32 / errors [31:0] $end
$var integer 32 0 mode [31:0] $end
$scope module spi_slave1 $end
$var wire 8 1 Add2_in [7:0] $end
$var wire 1 & CPHA $end
$var wire 1 ' CPOL $end
$var wire 1 % Clk $end
$var wire 1 2 LeadingEdge $end
$var wire 1 * MOSI $end
$var wire 1 - SCK $end
$var wire 1 3 SCK_norm0 $end
$var wire 1 4 SCK_norm1 $end
$var wire 1 . SSEL $end
$var wire 1 5 TrailingEdge $end
$var wire 1 + iRST_N $end
$var wire 1 6 SampleEdge $end
$var wire 1 7 DriveEdge $end
$var reg 8 8 Add_SPI [7:0] $end
$var reg 4 9 BitCnt [3:0] $end
$var reg 1 : CPHA_delay0 $end
$var reg 1 ; CPHA_latched $end
$var reg 1 < CPHA_metastable $end
$var reg 1 = CPOL_delay0 $end
$var reg 1 > CPOL_latched $end
$var reg 1 ? CPOL_metastable $end
$var reg 8 @ Data2_out [7:0] $end
$var reg 8 A DataToSend [7:0] $end
$var reg 8 B Data_fromSPI [7:0] $end
$var reg 8 C Data_toSPI [7:0] $end
$var reg 1 ! MISO $end
$var reg 1 D MOSI_delay0 $end
$var reg 1 E MOSI_metastable $end
$var reg 8 F ReceivedByte [7:0] $end
$var reg 8 G Register0 [7:0] $end
$var reg 8 H Register1 [7:0] $end
$var reg 8 I Register2 [7:0] $end
$var reg 8 J Register3 [7:0] $end
$var reg 8 K Register4 [7:0] $end
$var reg 8 L Register5 [7:0] $end
$var reg 8 M Register6 [7:0] $end
$var reg 8 N Register7 [7:0] $end
$var reg 1 O RnW $end
$var reg 1 P SCK_delay0 $end
$var reg 1 Q SCK_delay1 $end
$var reg 1 R SCK_metastable $end
$var reg 3 S SPI_State [2:0] $end
$var reg 1 T SSEL_delay0 $end
$var reg 1 U SSEL_delay1 $end
$var reg 1 V SSEL_metastable $end
$var reg 1 W WrEn $end
$var reg 8 X debug [7:0] $end
$upscope $end
$scope task run_mode $end
$var reg 2 Y m [1:0] $end
$upscope $end
$scope task spi_xfer_byte $end
$var reg 8 Z rx [7:0] $end
$var reg 8 [ tx [7:0] $end
$var integer 32 \ i [31:0] $end
$upscope $end
$upscope $end
$enddefinitions $end
$comment Show the parameter values. $end
$dumpall
$end
#0
$dumpvars
bx \
bx [
bx Z
b0 Y
b0 X
0W
0V
0U
0T
b0 S
0R
0Q
0P
0O
b110000 N
b100000 M
b10000 L
b1110 K
b1101 J
b1100 I
b1011 H
b1010 G
b0 F
0E
0D
b0 C
b0 B
b0 A
b0 @
0?
0>
0=
0<
0;
0:
b0 9
b0 8
07
06
05
04
03
02
b11 1
b0 0
b0 /
1.
0-
bx ,
0+
0*
bx )
bx (
0'
0&
0%
b11 $
b0 #
b0 "
0!
$end
#1
1%
#2
0%
#3
1%
#4
0%
#5
1%
#6
0%
#7
1%
#8
0%
#9
1%
#10
0%
#11
1%
#12
0%
#13
1%
#14
0%
#15
1%
#16
0%
#17
1%
#18
0%
#19
1%
#20
0%
1+
#21
b1 "
b1 X
1V
b1101 #
b1101 @
1%
#22
0%
#23
1T
1%
#24
0%
#25
1U
1%
#26
0%
#27
1%
#28
0%
#29
1%
#30
0%
#31
1%
#32
0%
#33
1%
#34
0%
#35
1%
#36
0%
#37
1%
#38
0%
#39
1%
#40
0%
0.
#41
0V
1%
#42
0%
#43
0T
1%
#44
0%
#45
b1 S
0U
1%
#46
0%
#47
b11 "
b11 X
1%
#48
0%
#49
1%
#50
0%
1*
b111 \
b10000001 [
#51
1E
1%
#52
0%
#53
1D
1%
#54
0%
#55
1%
#56
0%
#57
1%
#58
0%
#59
1%
#60
0%
b0xxxxxxx Z
1-
#61
1R
1%
#62
0%
#63
16
12
13
1P
1%
#64
0%
#65
06
02
14
b1 9
b1 F
1Q
1%
#66
0%
#67
1%
#68
0%
#69
1%
#70
0%
0*
b110 \
0-
#71
0E
0R
1%
#72
0%
#73
17
15
03
0D
0P
1%
#74
0%
#75
07
05
04
0Q
1%
#76
0%
#77
1%
#78
0%
#79
1%
#80
0%
b0xxxxxx Z
1-
#81
1R
1%
#82
0%
#83
16
12
13
1P
1%
#84
0%
#85
06
02
14
b10 9
b10 F
1Q
1%
#86
0%
#87
1%
#88
0%
#89
1%
#90
0%
b101 \
0-
#91
0R
1%
#92
0%
#93
17
15
03
0P
1%
#94
0%
#95
07
05
04
0Q
1%
#96
0%
#97
1%
#98
0%
#99
1%
#100
0%
b0xxxxx Z
1-
#101
1R
1%
#102
0%
#103
16
12
13
1P
1%
#104
0%
#105
06
02
14
b11 9
b100 F
1Q
1%
#106
0%
#107
1%
#108
0%
#109
1%
#110
0%
b100 \
0-
#111
0R
1%
#112
0%
#113
17
15
03
0P
1%
#114
0%
#115
07
05
04
0Q
1%
#116
0%
#117
1%
#118
0%
#119
1%
#120
0%
b0xxxx Z
1-
#121
1R
1%
#122
0%
#123
16
12
13
1P
1%
#124
0%
#125
06
02
14
b100 9
b1000 F
1Q
1%
#126
0%
#127
1%
#128
0%
#129
1%
#130
0%
b11 \
0-
#131
0R
1%
#132
0%
#133
17
15
03
0P
1%
#134
0%
#135
07
05
04
0Q
1%
#136
0%
#137
1%
#138
0%
#139
1%
#140
0%
b0xxx Z
1-
#141
1R
1%
#142
0%
#143
16
12
13
1P
1%
#144
0%
#145
06
02
14
b101 9
b10000 F
1Q
1%
#146
0%
#147
1%
#148
0%
#149
1%
#150
0%
b10 \
0-
#151
0R
1%
#152
0%
#153
17
15
03
0P
1%
#154
0%
#155
07
05
04
0Q
1%
#156
0%
#157
1%
#158
0%
#159
1%
#160
0%
b0xx Z
1-
#161
1R
1%
#162
0%
#163
16
12
13
1P
1%
#164
0%
#165
06
02
14
b110 9
b100000 F
1Q
1%
#166
0%
#167
1%
#168
0%
#169
1%
#170
0%
b1 \
0-
#171
0R
1%
#172
0%
#173
17
15
03
0P
1%
#174
0%
#175
07
05
04
0Q
1%
#176
0%
#177
1%
#178
0%
#179
1%
#180
0%
b0x Z
1-
#181
1R
1%
#182
0%
#183
16
12
13
1P
1%
#184
0%
#185
06
02
14
b111 9
b1000000 F
1Q
1%
#186
0%
#187
1%
#188
0%
#189
1%
#190
0%
1*
b0 \
0-
#191
1E
0R
1%
#192
0%
#193
17
15
03
1D
0P
1%
#194
0%
#195
07
05
04
0Q
1%
#196
0%
#197
1%
#198
0%
#199
1%
#200
0%
b0 Z
1-
#201
1R
1%
#202
0%
#203
16
12
13
1P
1%
#204
0%
#205
06
02
14
b1000 9
b10000001 F
1Q
1%
#206
0%
#207
b11 S
1O
b1 8
b0 9
1%
#208
0%
#209
b1011 "
b1011 X
b1011 C
1%
#210
0%
0*
b0 [
b0 ,
b111 \
0-
#211
0E
0R
1%
#212
0%
#213
17
15
03
0D
0P
1%
#214
0%
#215
07
05
04
b1 9
b10110 A
0Q
1%
#216
0%
#217
1%
#218
0%
#219
1%
#220
0%
1-
#221
1R
1%
#222
0%
#223
16
12
13
1P
1%
#224
0%
#225
06
02
14
1Q
1%
#226
0%
#227
1%
#228
0%
#229
1%
#230
0%
b110 \
0-
#231
0R
1%
#232
0%
#233
17
15
03
0P
1%
#234
0%
#235
07
05
04
b10 9
b101100 A
0Q
1%
#236
0%
#237
1%
#238
0%
#239
1%
#240
0%
1-
#241
1R
1%
#242
0%
#243
16
12
13
1P
1%
#244
0%
#245
06
02
14
1Q
1%
#246
0%
#247
1%
#248
0%
#249
1%
#250
0%
b101 \
0-
#251
0R
1%
#252
0%
#253
17
15
03
0P
1%
#254
0%
#255
07
05
04
b11 9
b1011000 A
0Q
1%
#256
0%
#257
1%
#258
0%
#259
1%
#260
0%
1-
#261
1R
1%
#262
0%
#263
16
12
13
1P
1%
#264
0%
#265
06
02
14
1Q
1%
#266
0%
#267
1%
#268
0%
#269
1%
#270
0%
b100 \
0-
#271
0R
1%
#272
0%
#273
17
15
03
0P
1%
#274
0%
#275
07
05
04
b100 9
b10110000 A
0Q
1%
#276
0%
#277
1%
#278
0%
#279
1%
#280
0%
1-
#281
1R
1%
#282
0%
#283
16
12
13
1P
1%
#284
0%
#285
06
02
14
1Q
1%
#286
0%
#287
1%
#288
0%
#289
1%
#290
0%
b11 \
0-
#291
0R
1%
#292
0%
#293
17
15
03
0P
1%
#294
0%
#295
07
05
04
b101 9
b1100000 A
1!
0Q
1%
#296
0%
#297
1%
#298
0%
#299
1%
#300
0%
b1000 Z
1-
#301
1R
1%
#302
0%
#303
16
12
13
1P
1%
#304
0%
#305
06
02
14
1Q
1%
#306
0%
#307
1%
#308
0%
#309
1%
#310
0%
b10 \
0-
#311
0R
1%
#312
0%
#313
17
15
03
0P
1%
#314
0%
#315
07
05
04
b110 9
b11000000 A
0!
0Q
1%
#316
0%
#317
1%
#318
0%
#319
1%
#320
0%
1-
#321
1R
1%
#322
0%
#323
16
12
13
1P
1%
#324
0%
#325
06
02
14
1Q
1%
#326
0%
#327
1%
#328
0%
#329
1%
#330
0%
b1 \
0-
#331
0R
1%
#332
0%
#333
17
15
03
0P
1%
#334
0%
#335
07
05
04
b111 9
b10000000 A
1!
0Q
1%
#336
0%
#337
1%
#338
0%
#339
1%
#340
0%
b1010 Z
1-
#341
1R
1%
#342
0%
#343
16
12
13
1P
1%
#344
0%
#345
06
02
14
1Q
1%
#346
0%
#347
1%
#348
0%
#349
1%
#350
0%
b0 \
0-
#351
0R
1%
#352
0%
#353
17
15
03
0P
1%
#354
0%
#355
07
05
04
b1000 9
b0 A
0Q
1%
#356
0%
#357
b100 S
b10000001 B
1%
#358
0%
#359
b11011 "
b11011 X
1%
#360
0%
b1011 Z
1-
#361
1R
1%
#362
0%
#363
16
12
13
1P
1%
#364
0%
#365
06
02
14
1Q
1%
#366
0%
#367
1%
#368
0%
#369
1%
#370
0%
b1011 (
b11111111111111111111111111111111 \
0-
#371
0R
1%
#372
0%
#373
17
15
03
0P
1%
#374
0%
#375
07
05
04
0Q
1%
#376
0%
#377
1%
#378
0%
#379
1%
#380
0%
1.
#381
1V
1%
#382
0%
#383
1T
1%
#384
0%
#385
b0 S
1U
1%
#386
0%
#387
b0 9
1%
#388
0%
#389
1%
#390
0%
#391
1%
#392
0%
#393
1%
#394
0%
#395
1%
#396
0%
#397
1%
#398
0%
#399
1%
#400
0%
0.
#401
0V
1%
#402
0%
#403
0T
1%
#404
0%
#405
b1 S
0U
1%
#406
0%
#407
1%
#408
0%
#409
1%
#410
0%
b111 \
b11 [
#411
1%
#412
0%
#413
1%
#414
0%
#415
1%
#416
0%
#417
1%
#418
0%
#419
1%
#420
0%
b10001011 Z
1-
#421
1R
1%
#422
0%
#423
16
12
13
1P
1%
#424
0%
#425
06
02
14
b1 9
b10 F
1Q
1%
#426
0%
#427
1%
#428
0%
#429
1%
#430
0%
b110 \
0-
#431
0R
1%
#432
0%
#433
17
15
03
0P
1%
#434
0%
#435
07
05
04
0Q
1%
#436
0%
#437
1%
#438
0%
#439
1%
#440
0%
b11001011 Z
1-
#441
1R
1%
#442
0%
#443
16
12
13
1P
1%
#444
0%
#445
06
02
14
b10 9
b100 F
1Q
1%
#446
0%
#447
1%
#448
0%
#449
1%
#450
0%
b101 \
0-
#451
0R
1%
#452
0%
#453
17
15
03
0P
1%
#454
0%
#455
07
05
04
0Q
1%
#456
0%
#457
1%
#458
0%
#459
1%
#460
0%
b11101011 Z
1-
#461
1R
1%
#462
0%
#463
16
12
13
1P
1%
#464
0%
#465
06
02
14
b11 9
b1000 F
1Q
1%
#466
0%
#467
1%
#468
0%
#469
1%
#470
0%
b100 \
0-
#471
0R
1%
#472
0%
#473
17
15
03
0P
1%
#474
0%
#475
07
05
04
0Q
1%
#476
0%
#477
1%
#478
0%
#479
1%
#480
0%
b11111011 Z
1-
#481
1R
1%
#482
0%
#483
16
12
13
1P
1%
#484
0%
#485
06
02
14
b100 9
b10000 F
1Q
1%
#486
0%
#487
1%
#488
0%
#489
1%
#490
0%
b11 \
0-
#491
0R
1%
#492
0%
#493
17
15
03
0P
1%
#494
0%
#495
07
05
04
0Q
1%
#496
0%
#497
1%
#498
0%
#499
1%
#500
0%
1-
#501
1R
1%
#502
0%
#503
16
12
13
1P
1%
#504
0%
#505
06
02
14
b101 9
b100000 F
1Q
1%
#506
0%
#507
1%
#508
0%
#509
1%
#510
0%
b10 \
0-
#511
0R
1%
#512
0%
#513
17
15
03
0P
1%
#514
0%
#515
07
05
04
0Q
1%
#516
0%
#517
1%
#518
0%
#519
1%
#520
0%
b11111111 Z
1-
#521
1R
1%
#522
0%
#523
16
12
13
1P
1%
#524
0%
#525
06
02
14
b110 9
b1000000 F
1Q
1%
#526
0%
#527
1%
#528
0%
#529
1%
#530
0%
1*
b1 \
0-
#531
1E
0R
1%
#532
0%
#533
17
15
03
1D
0P
1%
#534
0%
#535
07
05
04
0Q
1%
#536
0%
#537
1%
#538
0%
#539
1%
#540
0%
1-
#541
1R
1%
#542
0%
#543
16
12
13
1P
1%
#544
0%
#545
06
02
14
b111 9
b10000001 F
1Q
1%
#546
0%
#547
1%
#548
0%
#549
1%
#550
0%
b0 \
0-
#551
0R
1%
#552
0%
#553
17
15
03
0P
1%
#554
0%
#555
07
05
04
0Q
1%
#556
0%
#557
1%
#558
0%
#559
1%
#560
0%
1-
#561
1R
1%
#562
0%
#563
16
12
13
1P
1%
#564
0%
#565
06
02
14
b1000 9
b11 F
1Q
1%
#566
0%
#567
b10 S
0O
b11 8
b0 9
1%
#568
0%
#569
b11111 "
b11111 X
1%
#570
0%
b10100000 [
b11111111 ,
b111 \
0-
#571
0R
1%
#572
0%
#573
17
15
03
0P
1%
#574
0%
#575
07
05
04
0Q
1%
#576
0%
#577
1%
#578
0%
#579
1%
#580
0%
1-
#581
1R
1%
#582
0%
#583
16
12
13
1P
1%
#584
0%
#585
06
02
14
b1 9
b111 F
1Q
1%
#586
0%
#587
1%
#588
0%
#589
1%
#590
0%
0*
b110 \
0-
#591
0E
0R
1%
#592
0%
#593
17
15
03
0D
0P
1%
#594
0%
#595
07
05
04
0Q
1%
#596
0%
#597
1%
#598
0%
#599
1%
#600
0%
1-
#601
1R
1%
#602
0%
#603
16
12
13
1P
1%
#604
0%
#605
06
02
14
b10 9
b1110 F
1Q
1%
#606
0%
#607
1%
#608
0%
#609
1%
#610
0%
1*
b101 \
0-
#611
1E
0R
1%
#612
0%
#613
17
15
03
1D
0P
1%
#614
0%
#615
07
05
04
0Q
1%
#616
0%
#617
1%
#618
0%
#619
1%
#620
0%
1-
#621
1R
1%
#622
0%
#623
16
12
13
1P
1%
#624
0%
#625
06
02
14
b11 9
b11101 F
1Q
1%
#626
0%
#627
1%
#628
0%
#629
1%
#630
0%
0*
b100 \
0-
#631
0E
0R
1%
#632
0%
#633
17
15
03
0D
0P
1%
#634
0%
#635
07
05
04
0Q
1%
#636
0%
#637
1%
#638
0%
#639
1%
#640
0%
1-
#641
1R
1%
#642
0%
#643
16
12
13
1P
1%
#644
0%
#645
06
02
14
b100 9
b111010 F
1Q
1%
#646
0%
#647
1%
#648
0%
#649
1%
#650
0%
b11 \
0-
#651
0R
1%
#652
0%
#653
17
15
03
0P
1%
#654
0%
#655
07
05
04
0Q
1%
#656
0%
#657
1%
#658
0%
#659
1%
#660
0%
1-
#661
1R
1%
#662
0%
#663
16
12
13
1P
1%
#664
0%
#665
06
02
14
b101 9
b1110100 F
1Q
1%
#666
0%
#667
1%
#668
0%
#669
1%
#670
0%
b10 \
0-
#671
0R
1%
#672
0%
#673
17
15
03
0P
1%
#674
0%
#675
07
05
04
0Q
1%
#676
0%
#677
1%
#678
0%
#679
1%
#680
0%
1-
#681
1R
1%
#682
0%
#683
16
12
13
1P
1%
#684
0%
#685
06
02
14
b110 9
b11101000 F
1Q
1%
#686
0%
#687
1%
#688
0%
#689
1%
#690
0%
b1 \
0-
#691
0R
1%
#692
0%
#693
17
15
03
0P
1%
#694
0%
#695
07
05
04
0Q
1%
#696
0%
#697
1%
#698
0%
#699
1%
#700
0%
1-
#701
1R
1%
#702
0%
#703
16
12
13
1P
1%
#704
0%
#705
06
02
14
b111 9
b11010000 F
1Q
1%
#706
0%
#707
1%
#708
0%
#709
1%
#710
0%
b0 \
0-
#711
0R
1%
#712
0%
#713
17
15
03
0P
1%
#714
0%
