spi_slave.v
// Koen Van Caekenberghe (koen.vancaekenberghe@chipdesign.be), ChipDesign B.V., 06.2026
// SPI Slave
//
// - SPI mode: 0 (CPOL: 0, CPHA: 0)
// - Address range: 2^7. MSB bit of address byte is used for SPI command bit (SPI_READ_COMMAND=0, SPI_WRITE_COMMAND=1)
// - Register width: 1 byte 

`define STATE_SPI_IDLE 		3'd0
`define STATE_SPI_COMMAND	3'd1
`define STATE_SPI_WRITE 	3'd2
`define STATE_SPI_READ 		3'd3
`define STATE_SPI_END 		3'd4

`define ERROR_ADD_OUT_OF_RANGE 	8'hFF

module spi_slave
(
	input Clk,
	input iRST_N,
	
	input SCK, 
	input MOSI,
	input SSEL, 
	output reg MISO,
	
	input [7:0] Add2_in,	
	output reg [7:0] Data2_out,
	
	output reg [7:0] debug
);

reg [7:0] Register0, Register1, Register2, Register3, Register4, Register5, Register6, Register7;

reg SCK_metastable, MOSI_metastable, SSEL_metastable;
reg SCK_delay0, MOSI_delay0, SSEL_delay0;
reg SCK_delay1, SSEL_delay1;
reg WrEn, RnW;
reg [3:0] BitCnt;
reg [7:0] ReceivedByte, Data_fromSPI, DataToSend, Data_toSPI, Add_SPI;
reg [2:0] SPI_State;

always @(posedge Clk or negedge iRST_N) begin
	if(!iRST_N) begin
		Register0	<= 8'h0A;
		Register1	<= 8'h0B;
		Register2	<= 8'h0C;
		Register3	<= 8'h0D;
		Register4	<= 8'h0E;
		Register5	<= 8'h10;
		Register6	<= 8'h20;
		Register7	<= 8'h30;
		Data_toSPI 	<= 8'h00;
		Data2_out	<= 8'h00;
		
		SCK_metastable 	<= 1'b0;
		MOSI_metastable <= 1'b0;
		SSEL_metastable <= 1'b0;
		SCK_delay0 	<= 1'b0;	
		MOSI_delay0 	<= 1'b0; 
		SSEL_delay0 	<= 1'b0;
		SCK_delay1 	<= 1'b0;
		SSEL_delay1 	<= 1'b0;
		WrEn 		<= 1'b0;
		RnW		<= 1'b0;
		BitCnt		<= 4'h0;
		ReceivedByte	<= 8'h00;	
		Data_fromSPI	<= 8'h00;
		DataToSend	<= 8'h00;
		Add_SPI		<= 8'h00;
		
		MISO		<= 1'b0;
		
		debug		<= 1'b0;
		
		SPI_State 	<= `STATE_SPI_IDLE;
	end
	else begin
	
		//{{{ READ/WRITE ACCESS
		if (RnW) begin
			case (Add_SPI)
				8'h00: Data_toSPI <= Register0;
				8'h01: Data_toSPI <= Register1;
				8'h02: Data_toSPI <= Register2;
				8'h03: Data_toSPI <= Register3;
				8'h04: Data_toSPI <= Register4;
				8'h05: Data_toSPI <= Register5;
				8'h06: Data_toSPI <= Register6;
				8'h07: Data_toSPI <= Register7;
				default: Data_toSPI <= `ERROR_ADD_OUT_OF_RANGE;
			endcase
		end
		else if (WrEn) begin
			case (Add_SPI)
				8'h00:  Register0 <= Data_fromSPI;
				8'h01:  Register1 <= Data_fromSPI;
				8'h02:  Register2 <= Data_fromSPI;
				8'h03:  Register3 <= Data_fromSPI;
				8'h04:  Register4 <= Data_fromSPI;
				8'h05:  Register5 <= Data_fromSPI;
				8'h06:  Register6 <= Data_fromSPI;
				8'h07:  Register7 <= Data_fromSPI;
			endcase
		end		
		//}}}
		
		//{{{ READ ACCESS 2
		case (Add2_in)
			8'h00: Data2_out <= Register0;
			8'h01: Data2_out <= Register1;
			8'h02: Data2_out <= Register2;
			8'h03: Data2_out <= Register3;
			8'h04: Data2_out <= Register4;
			8'h05: Data2_out <= Register5;
			8'h06: Data2_out <= Register6;
			8'h07: Data2_out <= Register7;
			default: Data2_out <= `ERROR_ADD_OUT_OF_RANGE;
		endcase
		//}}}
		
		//{{{ SPI INTERFACE		
		SCK_metastable 	<= SCK;
		MOSI_metastable <= MOSI;
		SSEL_metastable <= SSEL;
		SCK_delay0 	<= SCK_metastable;	
		MOSI_delay0 	<= MOSI_metastable; 
		SSEL_delay0 	<= SSEL_metastable;
		SCK_delay1 	<= SCK_delay0;
		SSEL_delay1 	<= SSEL_delay0;
		
		WrEn 		<= 1'b0;

		case (SPI_State)		
		
			`STATE_SPI_IDLE: begin
				BitCnt <= 0;
				debug <= debug | 1;
				if (SSEL_delay0 == 0  && SSEL_delay1 == 1)
					SPI_State <= `STATE_SPI_COMMAND;
			end
			
			`STATE_SPI_COMMAND: begin
				debug <= debug | 8'h02;
				if (SCK_delay0 == 1 && SCK_delay1 == 0) begin
					ReceivedByte <= {ReceivedByte[6:0], MOSI_delay0};
					BitCnt <= BitCnt + 1;
				end
				if (BitCnt == 4'h8) begin
					BitCnt 	<= 4'h0;
					Add_SPI	<= {1'b0, ReceivedByte[6:0]};
					RnW 	<= ReceivedByte[7];
					if (ReceivedByte[7] == 1)
						SPI_State <= `STATE_SPI_READ;
					else
						SPI_State <= `STATE_SPI_WRITE;
				end
			end
			
			`STATE_SPI_WRITE: begin
				debug <= debug | 4;
				if (SCK_delay0 == 1 && SCK_delay1 == 0) begin
					ReceivedByte <= {ReceivedByte[6:0], MOSI_delay0};
					BitCnt <= BitCnt + 1;
				end
				if (BitCnt == 4'h8) begin
					WrEn <= 1;		
					Data_fromSPI <= ReceivedByte;
					SPI_State <= `STATE_SPI_END;
				end
			end

			`STATE_SPI_READ: begin
				debug <= debug | 8;
				if (BitCnt == 0) begin
					if (SCK_delay0 == 0 && SCK_delay1 == 1) begin
						MISO <= Data_toSPI[7];
						DataToSend <= {Data_toSPI[6:0], 1'b0};
						BitCnt <= 1;
					end
				end
				else begin
					if (SCK_delay0 == 0 && SCK_delay1 == 1) begin
						MISO <= DataToSend[7];
						DataToSend <= {DataToSend[6:0], 1'b0};
						BitCnt <= BitCnt + 1;
					end
				end
				if (BitCnt == 4'h8) begin
					Data_fromSPI <= ReceivedByte;
					SPI_State <= `STATE_SPI_END;
				end
			end
					
			`STATE_SPI_END: begin
				debug <= debug | 16;
				if (SSEL_delay0)
					SPI_State <= `STATE_SPI_IDLE;				
			end	
						
		endcase
		//}}}

	end
end

endmodule

tb_spi_slave_compare.v
// Koen Van Caekenberghe (koen.vancaekenberghe@chipdesign.be), ChipDesign B.V., 06.2026
// Comparison test bench — RTL vs synthesised netlist
//
// Transactions:
//   Tx1: READ  Register1 (addr 0x01) — verifies reset value 0x0B on MISO
//   Tx2: WRITE 0xFF → Register7 (addr 0x07)
//   Tx3: READ  Register7 (addr 0x07) — confirms Tx2 write; expects 0xFF on MISO
//
// Compile for RTL:
//   iverilog -g2012 -o tb_rtl.out tb_spi_slave_compare.v && vvp tb_rtl.out
//
// Compile for synthesised netlist (SYNTH guard skips the `include so the
// netlist and its cell library are supplied on the command line instead):
//   iverilog -g2012 -DSYNTH -o tb_synth.out flow/spi_slave_synth.v tb_spi_slave_compare.v
//   vvp tb_synth.out

`timescale 1ns/1ns

`ifndef SYNTH
`include "spi_slave.v"
`endif

module tb_spi_slave_compare();

reg [7:0] addr;
reg clk;
initial begin
    clk = 0;
    forever #1 clk = ~clk;
end

wire [7:0] data;
wire [7:0] debug;
wire miso;
reg mosi;
reg rst_n;
reg sck;
reg ssel;

reg [7:0] miso_rx1;  // MISO byte captured during Tx1 READ
reg [7:0] miso_rx3;  // MISO byte captured during Tx3 READ

spi_slave spi_slave1(
    .Clk(clk),
    .iRST_N(rst_n),
    .SCK(sck),
    .MOSI(mosi),
    .SSEL(ssel),
    .MISO(miso),
    .Add2_in(addr),
    .Data2_out(data),
    .debug(debug)
);

// Send 8-bit command byte MSB-first; MOSI is set up 10 ns before each rising edge.
task spi_send_cmd;
    input [7:0] cmd;
    integer i;
    begin
        for (i = 7; i >= 0; i = i - 1) begin
            mosi = cmd[i];
            #10 sck = 1;
            #10 sck = 0;
        end
    end
endtask

// Send 8-bit write data byte MSB-first on MOSI.
task spi_write_data;
    input [7:0] tx;
    integer i;
    begin
        for (i = 7; i >= 0; i = i - 1) begin
            mosi = tx[i];
            #10 sck = 1;
            #10 sck = 0;
        end
    end
endtask

// Receive 8-bit read data from MISO, sampling on each rising SCK edge.
task spi_read_data;
    output [7:0] rx;
    integer i;
    begin
        for (i = 7; i >= 0; i = i - 1) begin
            #10 sck = 1;
            rx[i] = miso;
            #10 sck = 0;
        end
    end
endtask

initial begin
    addr  = 8'd1;   // parallel port initially at Register1 (reset value 0x0B)
    mosi  = 0;
    rst_n = 0;
    sck   = 0;
    ssel  = 1;
    #10 rst_n = 1;

    // --- Tx1: READ Register1 (addr_byte=0x81: RnW=1, addr=0x01) ---
    // Expected MISO: 0x0B (Register1 reset value)
    #10 ssel = 0;
    spi_send_cmd(8'h81);
    spi_read_data(miso_rx1);
    #10 ssel = 1;
    #10;

    // --- Tx2: WRITE 0xFF → Register7 (addr_byte=0x07: RnW=0, addr=0x07) ---
    addr = 8'd7;    // point parallel port at Register7 to observe the write
    #10 ssel = 0;
    spi_send_cmd(8'h07);
    spi_write_data(8'hFF);
    #10 ssel = 1;
    #10;

    // --- Tx3: READ Register7 (addr_byte=0x87: RnW=1, addr=0x07) ---
    // Expected MISO: 0xFF — confirms Tx2 write was committed
    #10 ssel = 0;
    spi_send_cmd(8'h87);
    spi_read_data(miso_rx3);
    #10 ssel = 1;
    #10;
end

// Self-checking assertions — evaluated after all transactions complete
initial begin
    #1100;
    $display("FINISH %0t: miso_rx1=0x%02X data=0x%02X miso_rx3=0x%02X debug=0x%02X",
             $time, miso_rx1, data, miso_rx3, debug);
    if (miso_rx1 !== 8'h0B)
        $display("FAIL Tx1 READ Reg1  : expected miso=0x0B, got 0x%02X", miso_rx1);
    if (data !== 8'hFF)
        $display("FAIL parallel Reg7  : expected data=0xFF, got 0x%02X", data);
    if (miso_rx3 !== 8'hFF)
        $display("FAIL Tx3 READ Reg7  : expected miso=0xFF, got 0x%02X", miso_rx3);
    if (debug !== 8'h1F)
        $display("FAIL debug          : expected 0x1F, got 0x%02X", debug);
    if (miso_rx1 === 8'h0B && data === 8'hFF && miso_rx3 === 8'hFF && debug === 8'h1F)
        $display("PASS: all checks passed");
end

initial begin
    #1200 $finish;
end

initial begin
`ifdef SYNTH
    $dumpfile("tb_spi_slave_synth.vcd");
`else
    $dumpfile("tb_spi_slave_compare.vcd");
`endif
    $dumpvars(0, tb_spi_slave_compare);
end

endmodule

tb_spi_slave_compare.vcd
$date
	Sun Jun  7 14:23:05 2026
$end
$version
	Icarus Verilog
$end
$timescale
	1ns
$end
$scope module tb_spi_slave_compare $end
$var wire 1 ! miso $end
$var wire 8 " debug [7:0] $end
$var wire 8 # data [7:0] $end
$var reg 8 $ addr [7:0] $end
$var reg 1 % clk $end
$var reg 8 & miso_rx1 [7:0] $end
$var reg 8 ' miso_rx3 [7:0] $end
$var reg 1 ( mosi $end
$var reg 1 ) rst_n $end
$var reg 1 * sck $end
$var reg 1 + ssel $end
$scope module spi_slave1 $end
$var wire 8 , Add2_in [7:0] $end
$var wire 1 % Clk $end
$var wire 1 ( MOSI $end
$var wire 1 * SCK $end
$var wire 1 + SSEL $end
$var wire 1 ) iRST_N $end
$var reg 8 - Add_SPI [7:0] $end
$var reg 4 . BitCnt [3:0] $end
$var reg 8 / Data2_out [7:0] $end
$var reg 8 0 DataToSend [7:0] $end
$var reg 8 1 Data_fromSPI [7:0] $end
$var reg 8 2 Data_toSPI [7:0] $end
$var reg 1 ! MISO $end
$var reg 1 3 MOSI_delay0 $end
$var reg 1 4 MOSI_metastable $end
$var reg 8 5 ReceivedByte [7:0] $end
$var reg 8 6 Register0 [7:0] $end
$var reg 8 7 Register1 [7:0] $end
$var reg 8 8 Register2 [7:0] $end
$var reg 8 9 Register3 [7:0] $end
$var reg 8 : Register4 [7:0] $end
$var reg 8 ; Register5 [7:0] $end
$var reg 8 < Register6 [7:0] $end
$var reg 8 = Register7 [7:0] $end
$var reg 1 > RnW $end
$var reg 1 ? SCK_delay0 $end
$var reg 1 @ SCK_delay1 $end
$var reg 1 A SCK_metastable $end
$var reg 3 B SPI_State [2:0] $end
$var reg 1 C SSEL_delay0 $end
$var reg 1 D SSEL_delay1 $end
$var reg 1 E SSEL_metastable $end
$var reg 1 F WrEn $end
$var reg 8 G debug [7:0] $end
$upscope $end
$scope task spi_read_data $end
$var reg 8 H rx [7:0] $end
$var integer 32 I i [31:0] $end
$upscope $end
$scope task spi_send_cmd $end
$var reg 8 J cmd [7:0] $end
$var integer 32 K i [31:0] $end
$upscope $end
$scope task spi_write_data $end
$var reg 8 L tx [7:0] $end
$var integer 32 M i [31:0] $end
$upscope $end
$upscope $end
$enddefinitions $end
$comment Show the parameter values. $end
$dumpall
$end
#0
$dumpvars
bx M
bx L
bx K
bx J
bx I
bx H
b0 G
0F
0E
0D
0C
b0 B
0A
0@
0?
0>
b110000 =
b100000 <
b10000 ;
b1110 :
b1101 9
b1100 8
b1011 7
b1010 6
b0 5
04
03
b0 2
b0 1
b0 0
b0 /
b0 .
b0 -
b1 ,
1+
0*
0)
0(
bx '
bx &
0%
b1 $
b0 #
b0 "
0!
$end
#1
1%
#2
0%
#3
1%
#4
0%
#5
1%
#6
0%
#7
1%
#8
0%
#9
1%
#10
0%
1)
#11
b1 "
b1 G
1E
b1011 #
b1011 /
1%
#12
0%
#13
1C
1%
#14
0%
#15
1D
1%
#16
0%
#17
1%
#18
0%
#19
1%
#20
0%
1(
b111 K
b10000001 J
0+
#21
0E
14
1%
#22
0%
#23
0C
13
1%
#24
0%
#25
b1 B
0D
1%
#26
0%
#27
b11 "
b11 G
1%
#28
0%
#29
1%
#30
0%
1*
#31
1A
1%
#32
0%
#33
1?
1%
#34
0%
#35
b1 .
b1 5
1@
1%
#36
0%
#37
1%
#38
0%
#39
1%
#40
0%
0(
b110 K
0*
#41
04
0A
1%
#42
0%
#43
03
0?
1%
#44
0%
#45
0@
1%
#46
0%
#47
1%
#48
0%
#49
1%
#50
0%
1*
#51
1A
1%
#52
0%
#53
1?
1%
#54
0%
#55
b10 .
b10 5
1@
1%
#56
0%
#57
1%
#58
0%
#59
1%
#60
0%
b101 K
0*
#61
0A
1%
#62
0%
#63
0?
1%
#64
0%
#65
0@
1%
#66
0%
#67
1%
#68
0%
#69
1%
#70
0%
1*
#71
1A
1%
#72
0%
#73
1?
1%
#74
0%
#75
b11 .
b100 5
1@
1%
#76
0%
#77
1%
#78
0%
#79
1%
#80
0%
b100 K
0*
#81
0A
1%
#82
0%
#83
0?
1%
#84
0%
#85
0@
1%
#86
0%
#87
1%
#88
0%
#89
1%
#90
0%
1*
#91
1A
1%
#92
0%
#93
1?
1%
#94
0%
#95
b100 .
b1000 5
1@
1%
#96
0%
#97
1%
#98
0%
#99
1%
#100
0%
b11 K
0*
#101
0A
1%
#102
0%
#103
0?
1%
#104
0%
#105
0@
1%
#106
0%
#107
1%
#108
0%
#109
1%
#110
0%
1*
#111
1A
1%
#112
0%
#113
1?
1%
#114
0%
#115
b101 .
b10000 5
1@
1%
#116
0%
#117
1%
#118
0%
#119
1%
#120
0%
b10 K
0*
#121
0A
1%
#122
0%
#123
0?
1%
#124
0%
#125
0@
1%
#126
0%
#127
1%
#128
0%
#129
1%
#130
0%
1*
#131
1A
1%
#132
0%
#133
1?
1%
#134
0%
#135
b110 .
b100000 5
1@
1%
#136
0%
#137
1%
#138
0%
#139
1%
#140
0%
b1 K
0*
#141
0A
1%
#142
0%
#143
0?
1%
#144
0%
#145
0@
1%
#146
0%
#147
1%
#148
0%
#149
1%
#150
0%
1*
#151
1A
1%
#152
0%
#153
1?
1%
#154
0%
#155
b111 .
b1000000 5
1@
1%
#156
0%
#157
1%
#158
0%
#159
1%
#160
0%
1(
b0 K
0*
#161
14
0A
1%
#162
0%
#163
13
0?
1%
#164
0%
#165
0@
1%
#166
0%
#167
1%
#168
0%
#169
1%
#170
0%
1*
#171
1A
1%
#172
0%
#173
1?
1%
#174
0%
#175
b1000 .
b10000001 5
1@
1%
#176
0%
#177
b11 B
1>
b1 -
b0 .
1%
#178
0%
#179
b1011 "
b1011 G
b1011 2
1%
#180
0%
b111 I
b11111111111111111111111111111111 K
0*
#181
0A
1%
#182
0%
#183
0?
1%
#184
0%
#185
b1 .
b10110 0
0@
1%
#186
0%
#187
1%
#188
0%
#189
1%
#190
0%
b0xxxxxxx H
1*
#191
1A
1%
#192
0%
#193
1?
1%
#194
0%
#195
1@
1%
#196
0%
#197
1%
#198
0%
#199
1%
#200
0%
b110 I
0*
#201
0A
1%
#202
0%
#203
0?
1%
#204
0%
#205
b10 .
b101100 0
0@
1%
#206
0%
#207
1%
#208
0%
#209
1%
#210
0%
b0xxxxxx H
1*
#211
1A
1%
#212
0%
#213
1?
1%
#214
0%
#215
1@
1%
#216
0%
#217
1%
#218
0%
#219
1%
#220
0%
b101 I
0*
#221
0A
1%
#222
0%
#223
0?
1%
#224
0%
#225
b11 .
b1011000 0
0@
1%
#226
0%
#227
1%
#228
0%
#229
1%
#230
0%
b0xxxxx H
1*
#231
1A
1%
#232
0%
#233
1?
1%
#234
0%
#235
1@
1%
#236
0%
#237
1%
#238
0%
#239
1%
#240
0%
b100 I
0*
#241
0A
1%
#242
0%
#243
0?
1%
#244
0%
#245
b100 .
b10110000 0
0@
1%
#246
0%
#247
1%
#248
0%
#249
1%
#250
0%
b0xxxx H
1*
#251
1A
1%
#252
0%
#253
1?
1%
#254
0%
#255
1@
1%
#256
0%
#257
1%
#258
0%
#259
1%
#260
0%
b11 I
0*
#261
0A
1%
#262
0%
#263
0?
1%
#264
0%
#265
b101 .
b1100000 0
1!
0@
1%
#266
0%
#267
1%
#268
0%
#269
1%
#270
0%
b1xxx H
1*
#271
1A
1%
#272
0%
#273
1?
1%
#274
0%
#275
1@
1%
#276
0%
#277
1%
#278
0%
#279
1%
#280
0%
b10 I
0*
#281
0A
1%
#282
0%
#283
0?
1%
#284
0%
#285
b110 .
b11000000 0
0!
0@
1%
#286
0%
#287
1%
#288
0%
#289
1%
#290
0%
b10xx H
1*
#291
1A
1%
#292
0%
#293
1?
1%
#294
0%
#295
1@
1%
#296
0%
#297
1%
#298
0%
#299
1%
#300
0%
b1 I
0*
#301
0A
1%
#302
0%
#303
0?
1%
#304
0%
#305
b111 .
b10000000 0
1!
0@
1%
#306
0%
#307
1%
#308
0%
#309
1%
#310
0%
b101x H
1*
#311
1A
1%
#312
0%
#313
1?
1%
#314
0%
#315
1@
1%
#316
0%
#317
1%
#318
0%
#319
1%
#320
0%
b0 I
0*
#321
0A
1%
#322
0%
#323
0?
1%
#324
0%
#325
b1000 .
b0 0
0@
1%
#326
0%
#327
b100 B
b10000001 1
1%
#328
0%
#329
b11011 "
b11011 G
1%
#330
0%
b1011 H
1*
#331
1A
1%
#332
0%
#333
1?
1%
#334
0%
#335
1@
1%
#336
0%
#337
1%
#338
0%
#339
1%
#340
0%
b1011 &
b11111111111111111111111111111111 I
0*
#341
0A
1%
#342
0%
#343
0?
1%
#344
0%
#345
0@
1%
#346
0%
#347
1%
#348
0%
#349
1%
#350
0%
1+
#351
1E
1%
#352
0%
#353
1C
1%
#354
0%
#355
b0 B
1D
1%
#356
0%
#357
b0 .
1%
#358
0%
#359
1%
#360
0%
b111 $
b111 ,
#361
b110000 #
b110000 /
1%
#362
0%
#363
1%
#364
0%
#365
1%
#366
0%
#367
1%
#368
0%
#369
1%
#370
0%
0(
b111 K
b111 J
0+
#371
0E
04
1%
#372
0%
#373
0C
03
1%
#374
0%
#375
b1 B
0D
1%
#376
0%
#377
1%
#378
0%
#379
1%
#380
0%
1*
#381
1A
1%
#382
0%
#383
1?
1%
#384
0%
#385
b1 .
b10 5
1@
1%
#386
0%
#387
1%
#388
0%
#389
1%
#390
0%
b110 K
0*
#391
0A
1%
#392
0%
#393
0?
1%
#394
0%
#395
0@
1%
#396
0%
#397
1%
#398
0%
#399
1%
#400
0%
1*
#401
1A
1%
#402
0%
#403
1?
1%
#404
0%
#405
b10 .
b100 5
1@
1%
#406
0%
#407
1%
#408
0%
#409
1%
#410
0%
b101 K
0*
#411
0A
1%
#412
0%
#413
0?
1%
#414
0%
#415
0@
1%
#416
0%
#417
1%
#418
0%
#419
1%
#420
0%
1*
#421
1A
1%
#422
0%
#423
1?
1%
#424
0%
#425
b11 .
b1000 5
1@
1%
#426
0%
#427
1%
#428
0%
#429
1%
#430
0%
b100 K
0*
#431
0A
1%
#432
0%
#433
0?
1%
#434
0%
#435
0@
1%
#436
0%
#437
1%
#438
0%
#439
1%
#440
0%
1*
#441
1A
1%
#442
0%
#443
1?
1%
#444
0%
#445
b100 .
b10000 5
1@
1%
#446
0%
#447
1%
#448
0%
#449
1%
#450
0%
b11 K
0*
#451
0A
1%
#452
0%
#453
0?
1%
#454
0%
#455
0@
1%
#456
0%
#457
1%
#458
0%
#459
1%
#460
0%
1*
#461
1A
1%
#462
0%
#463
1?
1%
#464
0%
#465
b101 .
b100000 5
1@
1%
#466
0%
#467
1%
#468
0%
#469
1%
#470
0%
1(
b10 K
0*
#471
14
0A
1%
#472
0%
#473
13
0?
1%
#474
0%
#475
0@
1%
#476
0%
#477
1%
#478
0%
#479
1%
#480
0%
1*
#481
1A
1%
#482
0%
#483
1?
1%
#484
0%
#485
b110 .
b1000001 5
1@
1%
#486
0%
#487
1%
#488
0%
#489
1%
#490
0%
b1 K
0*
#491
0A
1%
#492
0%
#493
0?
1%
#494
0%
#495
0@
1%
#496
0%
#497
1%
#498
0%
#499
1%
#500
0%
1*
#501
1A
1%
#502
0%
#503
1?
1%
#504
0%
#505
b111 .
b10000011 5
1@
1%
#506
0%
#507
1%
#508
0%
#509
1%
#510
0%
b0 K
0*
#511
0A
1%
#512
0%
#513
0?
1%
#514
0%
#515
0@
1%
#516
0%
#517
1%
#518
0%
#519
1%
#520
0%
1*
#521
1A
1%
#522
0%
#523
1?
1%
#524
0%
#525
b1000 .
b111 5
1@
1%
#526
0%
#527
b10 B
0>
b111 -
b0 .
1%
#528
0%
#529
b11111 "
b11111 G
1%
#530
0%
b111 M
b11111111 L
b11111111111111111111111111111111 K
0*
#531
0A
1%
#532
0%
#533
0?
1%
#534
0%
#535
0@
1%
#536
0%
#537
1%
#538
0%
#539
1%
#540
0%
1*
#541
1A
1%
#542
0%
#543
1?
1%
#544
0%
#545
b1 .
b1111 5
1@
1%
#546
0%
#547
1%
#548
0%
#549
1%
#550
0%
b110 M
0*
#551
0A
1%
#552
0%
#553
0?
1%
#554
0%
#555
0@
1%
#556
0%
#557
1%
#558
0%
#559
1%
#560
0%
1*
#561
1A
1%
#562
0%
#563
1?
1%
#564
0%
#565
b10 .
b11111 5
1@
1%
#566
0%
#567
1%
#568
0%
#569
1%
#570
0%
b101 M
0*
#571
0A
1%
#572
0%
#573
0?
1%
#574
0%
#575
0@
1%
#576
0%
#577
1%
#578
0%
#579
1%
#580
0%
1*
#581
1A
1%
#582
0%
#583
1?
1%
#584
0%
#585
b11 .
b111111 5
1@
1%
#586
0%
#587
1%
#588
0%
#589
1%
#590
0%
b100 M
0*
#591
0A
1%
#592
0%
#593
0?
1%
#594
0%
#595
0@
1%
#596
0%
#597
1%
#598
0%
#599
1%
#600
0%
1*
#601
1A
1%
#602
0%
#603
1?
1%
#604
0%
#605
b100 .
b1111111 5
1@
1%
#606
0%
#607
1%
#608
0%
#609
1%
#610
0%
b11 M
0*
#611
0A
1%
#612
0%
#613
0?
1%
#614
0%
#615
0@
1%
#616
0%
#617
1%
#618
0%
#619
1%
#620
0%
1*
#621
1A
1%
#622
0%
#623
1?
1%
#624
0%
#625
b101 .
b11111111 5
1@
1%
#626
0%
#627
1%
#628
0%
#629
1%
#630
0%
b10 M
0*
#631
0A
1%
#632
0%
#633
0?
1%
#634
0%
#635
0@
1%
#636
0%
#637
1%
#638
0%
#639
1%
#640
0%
1*
#641
1A
1%
#642
0%
#643
1?
1%
#644
0%
#645
b110 .
1@
1%
#646
0%
#647
1%
#648
0%
#649
1%
#650
0%
b1 M
0*
#651
0A
1%
#652
0%
#653
0?
1%
#654
0%
#655
0@
1%
#656
0%
#657
1%
#658
0%
#659
1%
#660
0%
1*
#661
1A
1%
#662
0%
#663
1?
1%
#664
0%
#665
b111 .
1@
1%
#666
0%
#667
1%
#668
0%
#669
1%
#670
0%
b0 M
0*
#671
0A
1%
#672
0%
#673
0?
1%
#674
0%
#675
0@
1%
#676
0%
#677
1%
#678
0%
#679
1%
#680
0%
1*
#681
1A
1%
#682
0%
#683
1?
1%
#684
0%
#685
b1000 .
1@
1%
#686
0%
#687
b100 B
b11111111 1
1F
1%
#688
0%
#689
0F
b11111111 =
1%
#690
0%
b11111111111111111111111111111111 M
0*
#691
0A
b11111111 #
b11111111 /
1%
#692
0%
#693
0?
1%
#694
0%
#695
0@
1%
#696
0%
#697
1%
#698
0%
#699
1%
#700
0%
1+
#701
1E
1%
#702
0%
#703
1C
1%
#704
0%
#705
b0 B
1D
1%
#706
0%
#707
b0 .
1%
#708
0%
#709
1%
#710
0%
#711
1%
#712
0%
#713
1%
#714
0%
#715
1%
#716
0%
#717
1%
#718
0%
#719
1%
#720
0%
b111 K
b10000111 J
0+
#721
0E
1%
#722
0%
#723
0C
1%
#724
0%
#725
b1 B
0D
1%
#726
0%
#727
1%
#728
0%
#729
1%
#730
0%
1*
#731
1A
1%
#732
0%
#733
1?
1%
#734
0%
#735
b1 .
1@
1%
#736
0%
#737
1%
#738
0%
#739
1%
#740
0%
0(
b110 K
0*
#741
04
0A
1%
#742
0%
#743
03
0?
1%
#744
0%
#745
0@
1%
#746
0%
#747
1%
#748
0%
#749
1%
#750
0%
1*
#751
1A
1%
#752
0%
#753
1?
1%
#754
0%
#755
b10 .
b11111110 5
1@
1%
#756
0%
#757
1%
#758
0%
#759
1%
#760
0%
b101 K
0*
#761
0A
1%
#762
0%
#763
0?
1%
#764
0%
#765
0@
1%
#766
0%
#767
1%
#768
0%
#769
1%
#770
0%
1*
#771
1A
1%
#772
0%
#773
1?
1%
#774
0%
#775
b11 .
b11111100 5
1@
1%
#776
0%
#777
1%
#778
0%
#779
1%
#780
0%
b100 K
0*
#781
0A
1%
#782
0%
#783
0?
1%
#784
0%
#785
0@
1%
#786
0%
#787
1%
#788
0%
#789
1%
#790
0%
1*
#791
1A
1%
#792
0%
#793
1?
1%
#794
0%
#795
b100 .
b11111000 5
1@
1%
#796
0%
#797
1%
#798
0%
#799
1%
#800
0%
b11 K
0*
#801
0A
1%
#802
0%
#803
0?
1%
#804
0%
#805
0@
1%
#806
0%
#807
1%
#808
0%
#809
1%
#810
0%
1*
#811
1A
1%
#812
0%
#813
1?
1%
#814
0%
#815
b101 .
b11110000 5
1@
1%
#816
0%
#817
1%
#818
0%
#819
1%
#820
0%
1(
b10 K
0*
#821
14
0A
1%
#822
0%
#823
13
0?
1%
#824
0%
#825
0@
1%
#826
0%
#827
1%
#828
0%
#829
1%
#830
0%
1*
#831
1A
1%
#832
0%
#833
1?
1%
#834
0%
#835
b110 .
b11100001 5
1@
1%
#836
0%
#837
1%
#838
0%
#839
1%
#840
0%
b1 K
0*
#841
0A
1%
#842
0%
#843
0?
1%
#844
0%
#845
0@
1%
#846
0%
#847
1%
#848
0%
#849
1%
#850
0%
1*
#851
1A
1%
#852
0%
#853
1?
1%
#854
0%
#855
b111 .
b11000011 5
1@
1%
#856
0%
#857
1%
#858
0%
#859
1%
#860
0%
b0 K
0*
#861
0A
1%
#862
0%
#863
0?
1%
#864
0%
#865
0@
1%
#866
0%
#867
1%
#868
0%
#869
1%
#870
0%
1*
#871
1A
1%
#872
0%
#873
1?
1%
#874
0%
#875
b1000 .
b10000111 5
1@
1%
#876
0%
#877
b11 B
1>
b0 .
1%
#878
0%
#879
b11111111 2
1%
#880
0%
b111 I
b11111111111111111111111111111111 K
0*
#881
0A
1%
#882
0%
#883
0?
1%
#884
0%
#885
b1 .
b11111110 0
0@
1%
#886
0%
#887
1%
#888
0%
#889
1%
#890
0%
b10001011 H
1*
#891
1A
1%
#892
0%
#893
1?
1%
#894
0%
#895
1@
1%
#896
0%
#897
1%
#898
0%
#899
1%
#900
0%
b110 I
0*
#901
0A
1%
#902
0%
#903
0?
1%
#904
0%
#905
b10 .
b11111100 0
0@
1%
#906
0%
#907
1%
#908
0%
#909
1%
#910
0%
b11001011 H
1*
#911
1A
1%
#912
0%
#913
1?
1%
#914
0%
#915
1@
1%
#916
0%
#917
1%
#918
0%
#919
1%
#920
0%
b101 I
0*
#921
0A
1%
#922
0%
#923
0?
1%
#924
0%
#925
b11 .
b11111000 0
0@
1%
#926
0%
#927
1%
#928
0%
#929
1%
#930
0%
b11101011 H
1*
#931
1A
1%
#932
0%
#933
1?
1%
#934
0%
#935
1@
1%
#936
0%
#937
1%
#938
0%
#939
1%
#940
0%
b100 I
0*
#941
0A
1%
#942
0%
#943
0?
1%
#944
0%
#945
b100 .
b11110000 0
0@
1%
#946
0%
#947
1%
#948
0%
#949
1%
#950
0%
b11111011 H
1*
#951
1A
1%
#952
0%
#953
1?
1%
#954
0%
#955
1@
1%
#956
0%
#957
1%
#958
0%
#959
1%
#960
0%
b11 I
0*
#961
0A
1%
#962
0%
#963
0?
1%
#964
0%
#965
b101 .
b11100000 0
0@
1%
#966
0%
#967
1%
#968
0%
#969
1%
#970
0%
1*
#971
1A
1%
#972
0%
#973
1?
1%
#974
0%
#975
1@
1%
#976
0%
#977
1%
#978
0%
#979
1%
#980
0%
b10 I
0*
#981
0A
1%
#982
0%
#983
0?
1%
#984
0%
#985
b110 .
b11000000 0
0@
1%
#986
0%
#987
1%
#988
0%
#989
1%
#990
0%
b11111111 H
1*
#991
1A
1%
#992
0%
#993
1?
1%
#994
0%
#995
1@
1%
#996
0%
#997
1%
#998
0%
#999
1%
#1000
0%
b1 I
0*
#1001
0A
1%
#1002
0%
#1003
0?
1%
#1004
0%
#1005
b111 .
b10000000 0
0@
1%
#1006
0%
#1007
1%
#1008
0%
#1009
1%
