spi_slave.v
// Koen Van Caekenberghe (koen.vancaekenberghe@chipdesign.be), ChipDesign B.V., 06.2026
// SPI Slave
//
// - SPI mode: 0 (CPOL: 0, CPHA: 0)
// - Address range: 2^7. MSB bit of address byte is used for SPI command bit (SPI_READ_COMMAND=0, SPI_WRITE_COMMAND=1)
// - Register width: 1 byte 

`define STATE_SPI_IDLE 		3'd0
`define STATE_SPI_COMMAND	3'd1
`define STATE_SPI_WRITE 	3'd2
`define STATE_SPI_READ 		3'd3
`define STATE_SPI_END 		3'd4

`define ERROR_ADD_OUT_OF_RANGE 	8'hFF

module spi_slave
(
	input Clk,
	input iRST_N,
	
	input SCK, 
	input MOSI,
	input SSEL, 
	output reg MISO,
	
	input [7:0] Add2_in,	
	output reg [7:0] Data2_out,
	
	output reg [7:0] debug
);

reg [7:0] Register0, Register1, Register2, Register3, Register4, Register5, Register6, Register7;

reg SCK_metastable, MOSI_metastable, SSEL_metastable;
reg SCK_delay0, MOSI_delay0, SSEL_delay0;
reg SCK_delay1, SSEL_delay1;
reg WrEn, RnW;
reg [3:0] BitCnt;
reg [7:0] ReceivedByte, Data_fromSPI, DataToSend, Data_toSPI, Add_SPI;
reg [2:0] SPI_State;

always @(posedge Clk or negedge iRST_N) begin
	if(!iRST_N) begin
		Register0	<= 8'h0A;
		Register1	<= 8'h0B;
		Register2	<= 8'h0C;
		Register3	<= 8'h0D;
		Register4	<= 8'h0E;
		Register5	<= 8'h10;
		Register6	<= 8'h20;
		Register7	<= 8'h30;
		Data_toSPI 	<= 8'h00;
		Data2_out	<= 8'h00;
		
		SCK_metastable 	<= 1'b0;
		MOSI_metastable <= 1'b0;
		SSEL_metastable <= 1'b0;
		SCK_delay0 	<= 1'b0;	
		MOSI_delay0 	<= 1'b0; 
		SSEL_delay0 	<= 1'b0;
		SCK_delay1 	<= 1'b0;
		SSEL_delay1 	<= 1'b0;
		WrEn 		<= 1'b0;
		RnW		<= 1'b0;
		BitCnt		<= 4'h0;
		ReceivedByte	<= 8'h00;	
		Data_fromSPI	<= 8'h00;
		DataToSend	<= 8'h00;
		Add_SPI		<= 8'h00;
		
		MISO		<= 1'b0;
		
		debug		<= 1'b0;
		
		SPI_State 	<= `STATE_SPI_IDLE;
	end
	else begin
	
		//{{{ READ/WRITE ACCESS
		if (RnW) begin
			case (Add_SPI)
				8'h00: Data_toSPI <= Register0;
				8'h01: Data_toSPI <= Register1;
				8'h02: Data_toSPI <= Register2;
				8'h03: Data_toSPI <= Register3;
				8'h04: Data_toSPI <= Register4;
				8'h05: Data_toSPI <= Register5;
				8'h06: Data_toSPI <= Register6;
				8'h07: Data_toSPI <= Register7;
				default: Data_toSPI <= `ERROR_ADD_OUT_OF_RANGE;
			endcase
		end
		else if (WrEn) begin
			case (Add_SPI)
				8'h00:  Register0 <= Data_fromSPI;
				8'h01:  Register1 <= Data_fromSPI;
				8'h02:  Register2 <= Data_fromSPI;
				8'h03:  Register3 <= Data_fromSPI;
				8'h04:  Register4 <= Data_fromSPI;
				8'h05:  Register5 <= Data_fromSPI;
				8'h06:  Register6 <= Data_fromSPI;
				8'h07:  Register7 <= Data_fromSPI;
			endcase
		end		
		//}}}
		
		//{{{ READ ACCESS 2
		case (Add2_in)
			8'h00: Data2_out <= Register0;
			8'h01: Data2_out <= Register1;
			8'h02: Data2_out <= Register2;
			8'h03: Data2_out <= Register3;
			8'h04: Data2_out <= Register4;
			8'h05: Data2_out <= Register5;
			8'h06: Data2_out <= Register6;
			8'h07: Data2_out <= Register7;
			default: Data2_out <= `ERROR_ADD_OUT_OF_RANGE;
		endcase
		//}}}
		
		//{{{ SPI INTERFACE		
		SCK_metastable 	<= SCK;
		MOSI_metastable <= MOSI;
		SSEL_metastable <= SSEL;
		SCK_delay0 	<= SCK_metastable;	
		MOSI_delay0 	<= MOSI_metastable; 
		SSEL_delay0 	<= SSEL_metastable;
		SCK_delay1 	<= SCK_delay0;
		SSEL_delay1 	<= SSEL_delay0;
		
		WrEn 		<= 1'b0;

		case (SPI_State)		
		
			`STATE_SPI_IDLE: begin
				BitCnt <= 0;
				debug <= debug | 1;
				if (SSEL_delay0 == 0  && SSEL_delay1 == 1)
					SPI_State <= `STATE_SPI_COMMAND;
			end
			
			`STATE_SPI_COMMAND: begin
				debug <= debug | 8'h02;
				if (SCK_delay0 == 1 && SCK_delay1 == 0) begin
					ReceivedByte <= {ReceivedByte[6:0], MOSI_delay0};
					BitCnt <= BitCnt + 1;
				end
				if (BitCnt == 4'h8) begin
					BitCnt 	<= 4'h0;
					Add_SPI	<= {1'b0, ReceivedByte[6:0]};
					RnW 	<= ReceivedByte[7];
					if (ReceivedByte[7] == 1)
						SPI_State <= `STATE_SPI_READ;
					else
						SPI_State <= `STATE_SPI_WRITE;
				end
			end
			
			`STATE_SPI_WRITE: begin
				debug <= debug | 4;
				if (SCK_delay0 == 1 && SCK_delay1 == 0) begin
					ReceivedByte <= {ReceivedByte[6:0], MOSI_delay0};
					BitCnt <= BitCnt + 1;
				end
				if (BitCnt == 4'h8) begin
					WrEn <= 1;		
					Data_fromSPI <= ReceivedByte;
					SPI_State <= `STATE_SPI_END;
				end
			end

			`STATE_SPI_READ: begin
				debug <= debug | 8;
				if (BitCnt == 0) begin
					if (SCK_delay0 == 0 && SCK_delay1 == 1) begin
						MISO <= Data_toSPI[7];
						DataToSend <= {Data_toSPI[6:0], 1'b0};
						BitCnt <= 1;
					end
				end
				else begin
					if (SCK_delay0 == 0 && SCK_delay1 == 1) begin
						MISO <= DataToSend[7];
						DataToSend <= {DataToSend[6:0], 1'b0};
						BitCnt <= BitCnt + 1;
					end
				end
				if (BitCnt == 4'h8) begin
					Data_fromSPI <= ReceivedByte;
					SPI_State <= `STATE_SPI_END;
				end
			end
					
			`STATE_SPI_END: begin
				debug <= debug | 16;
				if (SSEL_delay0)
					SPI_State <= `STATE_SPI_IDLE;				
			end	
						
		endcase
		//}}}

	end
end

endmodule

tb_spi_slave.v
// Koen Van Caekenberghe (koen.vancaekenberghe@chipdesign.be), ChipDesign B.V., 06.2026
// Test bench for SPI Slave

// iverilog tb_spi_slave.v
// vvp a.out
// gtkwave tb_spi_slave.vcd

`include "spi_slave.v"
`timescale 1ns/1ns

module tb_spi_slave();

reg [7:0] addr; // IC internal register select
reg clk; // IC internal clock (PLL)
initial begin
 	clk=0;
	forever #1 clk = ~clk;
end

wire [7:0] data; // IC internal register output
wire [7:0] debug;
wire miso; // SPI MISO
reg mosi; // SPI MOSI
reg rst_n; // IC power-on-reset
reg sck; // SPI data clock
reg ssel; // SPI slave select

spi_slave spi_slave1(clk,rst_n,sck,mosi,ssel,miso,addr,data,debug);

// Transaction 1: READ Register1  (addr_byte=0x81: RnW=1, addr=0x01; default value 0x0B expected on MISO)
// Transaction 2: WRITE 0xFF to Register3 (addr_byte=0x03: RnW=0, addr=0x03; data_byte=0xFF)
initial begin
	addr=8'd3;
	mosi=0;
	rst_n=0;
 	sck=0;
	ssel=1;
	#10 rst_n=1;

	// --- Transaction 1: READ addr=0x01 (addr_byte=0x81) ---
	#10 ssel=0;
	#10 sck=1;
	mosi=1; // bit7: RnW=1 (Read)
	#10 sck=0;
	#10 sck=1;
	mosi=0; // bit6
	#10 sck=0;
	#10 sck=1;
	mosi=0; // bit5
	#10 sck=0;
	#10 sck=1;
	mosi=0; // bit4
	#10 sck=0;
	#10 sck=1;
	mosi=0; // bit3
	#10 sck=0;
	#10 sck=1;
	mosi=0; // bit2
	#10 sck=0;
	#10 sck=1;
	mosi=0; // bit1
	#10 sck=0;
	#10 sck=1;
	mosi=1; // bit0 (LSB) → addr=0x01
	#10 sck=0;
	// data phase: 8 clocks; MISO shifts out Register1 (reset value 0x0B)
	#10 sck=1;
	#10 sck=0;
	#10 sck=1;
	#10 sck=0;
	#10 sck=1;
	#10 sck=0;
	#10 sck=1;
	#10 sck=0;
	#10 sck=1;
	#10 sck=0;
	#10 sck=1;
	#10 sck=0;
	#10 sck=1;
	#10 sck=0;
	#10 sck=1;
	#10 sck=0;
	#10 ssel=1;

	// --- Transaction 2: WRITE 0xFF to addr=0x03 (addr_byte=0x03) ---
	#10 ssel=0;
	#10 sck=1;
	mosi=0; // bit7: RnW=0 (Write)
	#10 sck=0;
	#10 sck=1;
	mosi=0; // bit6
	#10 sck=0;
	#10 sck=1;
	mosi=0; // bit5
	#10 sck=0;
	#10 sck=1;
	mosi=0; // bit4
	#10 sck=0;
	#10 sck=1;
	mosi=0; // bit3
	#10 sck=0;
	#10 sck=1;
	mosi=0; // bit2
	#10 sck=0;
	#10 sck=1;
	mosi=1; // bit1
	#10 sck=0;
	#10 sck=1;
	mosi=1; // bit0 (LSB) → addr=0x03
	#10 sck=0;
	// data byte: 0xFF
	#10 sck=1;
	mosi=1; // bit7 (MSB)
	#10 sck=0;
	#10 sck=1;
	mosi=1; // bit6
	#10 sck=0;
	#10 sck=1;
	mosi=1; // bit5
	#10 sck=0;
	#10 sck=1;
	mosi=1; // bit4
	#10 sck=0;
	#10 sck=1;
	mosi=1; // bit3
	#10 sck=0;
	#10 sck=1;
	mosi=1; // bit2
	#10 sck=0;
	#10 sck=1;
	mosi=1; // bit1
	#10 sck=0;
	#10 sck=1;
	mosi=1; // bit0 (LSB) → data=0xFF
	#10 sck=0;
end

initial begin
	#750 $finish;
end

initial begin
	$dumpfile("tb_spi_slave.vcd");
	$dumpvars(0,tb_spi_slave);
end

//initial begin
//	$monitor("At time %t, Q = %h (%0d)",$time, Q, Q);
//end

endmodule

tb_spi_slave.vcd
$date
	Sun Jun  7 12:50:43 2026
$end
$version
	Icarus Verilog
$end
$timescale
	1ns
$end
$scope module tb_spi_slave $end
$var wire 1 ! miso $end
$var wire 8 " debug [7:0] $end
$var wire 8 # data [7:0] $end
$var reg 8 $ addr [7:0] $end
$var reg 1 % clk $end
$var reg 1 & mosi $end
$var reg 1 ' rst_n $end
$var reg 1 ( sck $end
$var reg 1 ) ssel $end
$scope module spi_slave1 $end
$var wire 8 * Add2_in [7:0] $end
$var wire 1 % Clk $end
$var wire 1 & MOSI $end
$var wire 1 ( SCK $end
$var wire 1 ) SSEL $end
$var wire 1 ' iRST_N $end
$var reg 8 + Add_SPI [7:0] $end
$var reg 4 , BitCnt [3:0] $end
$var reg 8 - Data2_out [7:0] $end
$var reg 8 . DataToSend [7:0] $end
$var reg 8 / Data_fromSPI [7:0] $end
$var reg 8 0 Data_toSPI [7:0] $end
$var reg 1 ! MISO $end
$var reg 1 1 MOSI_delay0 $end
$var reg 1 2 MOSI_metastable $end
$var reg 8 3 ReceivedByte [7:0] $end
$var reg 8 4 Register0 [7:0] $end
$var reg 8 5 Register1 [7:0] $end
$var reg 8 6 Register2 [7:0] $end
$var reg 8 7 Register3 [7:0] $end
$var reg 8 8 Register4 [7:0] $end
$var reg 8 9 Register5 [7:0] $end
$var reg 8 : Register6 [7:0] $end
$var reg 8 ; Register7 [7:0] $end
$var reg 1 < RnW $end
$var reg 1 = SCK_delay0 $end
$var reg 1 > SCK_delay1 $end
$var reg 1 ? SCK_metastable $end
$var reg 3 @ SPI_State [2:0] $end
$var reg 1 A SSEL_delay0 $end
$var reg 1 B SSEL_delay1 $end
$var reg 1 C SSEL_metastable $end
$var reg 1 D WrEn $end
$var reg 8 E debug [7:0] $end
$upscope $end
$upscope $end
$enddefinitions $end
$comment Show the parameter values. $end
$dumpall
$end
#0
$dumpvars
b0 E
0D
0C
0B
0A
b0 @
0?
0>
0=
0<
b110000 ;
b100000 :
b10000 9
b1110 8
b1101 7
b1100 6
b1011 5
b1010 4
b0 3
02
01
b0 0
b0 /
b0 .
b0 -
b0 ,
b0 +
b11 *
1)
0(
0'
0&
0%
b11 $
b0 #
b0 "
0!
$end
#1
1%
#2
0%
#3
1%
#4
0%
#5
1%
#6
0%
#7
1%
#8
0%
#9
1%
#10
0%
1'
#11
b1 "
b1 E
1C
b1101 #
b1101 -
1%
#12
0%
#13
1A
1%
#14
0%
#15
1B
1%
#16
0%
#17
1%
#18
0%
#19
1%
#20
0%
0)
#21
0C
1%
#22
0%
#23
0A
1%
#24
0%
#25
b1 @
0B
1%
#26
0%
#27
b11 "
b11 E
1%
#28
0%
#29
1%
#30
0%
1&
1(
#31
12
1?
1%
#32
0%
#33
11
1=
1%
#34
0%
#35
b1 ,
b1 3
1>
1%
#36
0%
#37
1%
#38
0%
#39
1%
#40
0%
0(
#41
0?
1%
#42
0%
#43
0=
1%
#44
0%
#45
0>
1%
#46
0%
#47
1%
#48
0%
#49
1%
#50
0%
0&
1(
#51
02
1?
1%
#52
0%
#53
01
1=
1%
#54
0%
#55
b10 ,
b10 3
1>
1%
#56
0%
#57
1%
#58
0%
#59
1%
#60
0%
0(
#61
0?
1%
#62
0%
#63
0=
1%
#64
0%
#65
0>
1%
#66
0%
#67
1%
#68
0%
#69
1%
#70
0%
1(
#71
1?
1%
#72
0%
#73
1=
1%
#74
0%
#75
b11 ,
b100 3
1>
1%
#76
0%
#77
1%
#78
0%
#79
1%
#80
0%
0(
#81
0?
1%
#82
0%
#83
0=
1%
#84
0%
#85
0>
1%
#86
0%
#87
1%
#88
0%
#89
1%
#90
0%
1(
#91
1?
1%
#92
0%
#93
1=
1%
#94
0%
#95
b100 ,
b1000 3
1>
1%
#96
0%
#97
1%
#98
0%
#99
1%
#100
0%
0(
#101
0?
1%
#102
0%
#103
0=
1%
#104
0%
#105
0>
1%
#106
0%
#107
1%
#108
0%
#109
1%
#110
0%
1(
#111
1?
1%
#112
0%
#113
1=
1%
#114
0%
#115
b101 ,
b10000 3
1>
1%
#116
0%
#117
1%
#118
0%
#119
1%
#120
0%
0(
#121
0?
1%
#122
0%
#123
0=
1%
#124
0%
#125
0>
1%
#126
0%
#127
1%
#128
0%
#129
1%
#130
0%
1(
#131
1?
1%
#132
0%
#133
1=
1%
#134
0%
#135
b110 ,
b100000 3
1>
1%
#136
0%
#137
1%
#138
0%
#139
1%
#140
0%
0(
#141
0?
1%
#142
0%
#143
0=
1%
#144
0%
#145
0>
1%
#146
0%
#147
1%
#148
0%
#149
1%
#150
0%
1(
#151
1?
1%
#152
0%
#153
1=
1%
#154
0%
#155
b111 ,
b1000000 3
1>
1%
#156
0%
#157
1%
#158
0%
#159
1%
#160
0%
0(
#161
0?
1%
#162
0%
#163
0=
1%
#164
0%
#165
0>
1%
#166
0%
#167
1%
#168
0%
#169
1%
#170
0%
1&
1(
#171
12
1?
1%
#172
0%
#173
11
1=
1%
#174
0%
#175
b1000 ,
b10000001 3
1>
1%
#176
0%
#177
b11 @
1<
b1 +
b0 ,
1%
#178
0%
#179
b1011 "
b1011 E
b1011 0
1%
#180
0%
0(
#181
0?
1%
#182
0%
#183
0=
1%
#184
0%
#185
b1 ,
b10110 .
0>
1%
#186
0%
#187
1%
#188
0%
#189
1%
#190
0%
1(
#191
1?
1%
#192
0%
#193
1=
1%
#194
0%
#195
1>
1%
#196
0%
#197
1%
#198
0%
#199
1%
#200
0%
0(
#201
0?
1%
#202
0%
#203
0=
1%
#204
0%
#205
b10 ,
b101100 .
0>
1%
#206
0%
#207
1%
#208
0%
#209
1%
#210
0%
1(
#211
1?
1%
#212
0%
#213
1=
1%
#214
0%
#215
1>
1%
#216
0%
#217
1%
#218
0%
#219
1%
#220
0%
0(
#221
0?
1%
#222
0%
#223
0=
1%
#224
0%
#225
b11 ,
b1011000 .
0>
1%
#226
0%
#227
1%
#228
0%
#229
1%
#230
0%
1(
#231
1?
1%
#232
0%
#233
1=
1%
#234
0%
#235
1>
1%
#236
0%
#237
1%
#238
0%
#239
1%
#240
0%
0(
#241
0?
1%
#242
0%
#243
0=
1%
#244
0%
#245
b100 ,
b10110000 .
0>
1%
#246
0%
#247
1%
#248
0%
#249
1%
#250
0%
1(
#251
1?
1%
#252
0%
#253
1=
1%
#254
0%
#255
1>
1%
#256
0%
#257
1%
#258
0%
#259
1%
#260
0%
0(
#261
0?
1%
#262
0%
#263
0=
1%
#264
0%
#265
b101 ,
b1100000 .
1!
0>
1%
#266
0%
#267
1%
#268
0%
#269
1%
#270
0%
1(
#271
1?
1%
#272
0%
#273
1=
1%
#274
0%
#275
1>
1%
#276
0%
#277
1%
#278
0%
#279
1%
#280
0%
0(
#281
0?
1%
#282
0%
#283
0=
1%
#284
0%
#285
b110 ,
b11000000 .
0!
0>
1%
#286
0%
#287
1%
#288
0%
#289
1%
#290
0%
1(
#291
1?
1%
#292
0%
#293
1=
1%
#294
0%
#295
1>
1%
#296
0%
#297
1%
#298
0%
#299
1%
#300
0%
0(
#301
0?
1%
#302
0%
#303
0=
1%
#304
0%
#305
b111 ,
b10000000 .
1!
0>
1%
#306
0%
#307
1%
#308
0%
#309
1%
#310
0%
1(
#311
1?
1%
#312
0%
#313
1=
1%
#314
0%
#315
1>
1%
#316
0%
#317
1%
#318
0%
#319
1%
#320
0%
0(
#321
0?
1%
#322
0%
#323
0=
1%
#324
0%
#325
b1000 ,
b0 .
0>
1%
#326
0%
#327
b100 @
b10000001 /
1%
#328
0%
#329
b11011 "
b11011 E
1%
#330
0%
1(
#331
1?
1%
#332
0%
#333
1=
1%
#334
0%
#335
1>
1%
#336
0%
#337
1%
#338
0%
#339
1%
#340
0%
0(
#341
0?
1%
#342
0%
#343
0=
1%
#344
0%
#345
0>
1%
#346
0%
#347
1%
#348
0%
#349
1%
#350
0%
1)
#351
1C
1%
#352
0%
#353
1A
1%
#354
0%
#355
b0 @
1B
1%
#356
0%
#357
b0 ,
1%
#358
0%
#359
1%
#360
0%
0)
#361
0C
1%
#362
0%
#363
0A
1%
#364
0%
#365
b1 @
0B
1%
#366
0%
#367
1%
#368
0%
#369
1%
#370
0%
0&
1(
#371
02
1?
1%
#372
0%
#373
01
1=
1%
#374
0%
#375
b1 ,
b10 3
1>
1%
#376
0%
#377
1%
#378
0%
#379
1%
#380
0%
0(
#381
0?
1%
#382
0%
#383
0=
1%
#384
0%
#385
0>
1%
#386
0%
#387
1%
#388
0%
#389
1%
#390
0%
1(
#391
1?
1%
#392
0%
#393
1=
1%
#394
0%
#395
b10 ,
b100 3
1>
1%
#396
0%
#397
1%
#398
0%
#399
1%
#400
0%
0(
#401
0?
1%
#402
0%
#403
0=
1%
#404
0%
#405
0>
1%
#406
0%
#407
1%
#408
0%
#409
1%
#410
0%
1(
#411
1?
1%
#412
0%
#413
1=
1%
#414
0%
#415
b11 ,
b1000 3
1>
1%
#416
0%
#417
1%
#418
0%
#419
1%
#420
0%
0(
#421
0?
1%
#422
0%
#423
0=
1%
#424
0%
#425
0>
1%
#426
0%
#427
1%
#428
0%
#429
1%
#430
0%
1(
#431
1?
1%
#432
0%
#433
1=
1%
#434
0%
#435
b100 ,
b10000 3
1>
1%
#436
0%
#437
1%
#438
0%
#439
1%
#440
0%
0(
#441
0?
1%
#442
0%
#443
0=
1%
#444
0%
#445
0>
1%
#446
0%
#447
1%
#448
0%
#449
1%
#450
0%
1(
#451
1?
1%
#452
0%
#453
1=
1%
#454
0%
#455
b101 ,
b100000 3
1>
1%
#456
0%
#457
1%
#458
0%
#459
1%
#460
0%
0(
#461
0?
1%
#462
0%
#463
0=
1%
#464
0%
#465
0>
1%
#466
0%
#467
1%
#468
0%
#469
1%
#470
0%
1(
#471
1?
1%
#472
0%
#473
1=
1%
#474
0%
#475
b110 ,
b1000000 3
1>
1%
#476
0%
#477
1%
#478
0%
#479
1%
#480
0%
0(
#481
0?
1%
#482
0%
#483
0=
1%
#484
0%
#485
0>
1%
#486
0%
#487
1%
#488
0%
#489
1%
#490
0%
1&
1(
#491
12
1?
1%
#492
0%
#493
11
1=
1%
#494
0%
#495
b111 ,
b10000001 3
1>
1%
#496
0%
#497
1%
#498
0%
#499
1%
#500
0%
0(
#501
0?
1%
#502
0%
#503
0=
1%
#504
0%
#505
0>
1%
#506
0%
#507
1%
#508
0%
#509
1%
#510
0%
1(
#511
1?
1%
#512
0%
#513
1=
1%
#514
0%
#515
b1000 ,
b11 3
1>
1%
#516
0%
#517
b10 @
0<
b11 +
b0 ,
1%
#518
0%
#519
b11111 "
b11111 E
1%
#520
0%
0(
#521
0?
1%
#522
0%
#523
0=
1%
#524
0%
#525
0>
1%
#526
0%
#527
1%
#528
0%
#529
1%
#530
0%
1(
#531
1?
1%
#532
0%
#533
1=
1%
#534
0%
#535
b1 ,
b111 3
1>
1%
#536
0%
#537
1%
#538
0%
#539
1%
#540
0%
0(
#541
0?
1%
#542
0%
#543
0=
1%
#544
0%
#545
0>
1%
#546
0%
#547
1%
#548
0%
#549
1%
#550
0%
1(
#551
1?
1%
#552
0%
#553
1=
1%
#554
0%
#555
b10 ,
b1111 3
1>
1%
#556
0%
#557
1%
#558
0%
#559
1%
#560
0%
0(
#561
0?
1%
#562
0%
#563
0=
1%
#564
0%
#565
0>
1%
#566
0%
#567
1%
#568
0%
#569
1%
#570
0%
1(
#571
1?
1%
#572
0%
#573
1=
1%
#574
0%
#575
b11 ,
b11111 3
1>
1%
#576
0%
#577
1%
#578
0%
#579
1%
#580
0%
0(
#581
0?
1%
#582
0%
#583
0=
1%
#584
0%
#585
0>
1%
#586
0%
#587
1%
#588
0%
#589
1%
#590
0%
1(
#591
1?
1%
#592
0%
#593
1=
1%
#594
0%
#595
b100 ,
b111111 3
1>
1%
#596
0%
#597
1%
#598
0%
#599
1%
#600
0%
0(
#601
0?
1%
#602
0%
#603
0=
1%
#604
0%
#605
0>
1%
#606
0%
#607
1%
#608
0%
#609
1%
#610
0%
1(
#611
1?
1%
#612
0%
#613
1=
1%
#614
0%
#615
b101 ,
b1111111 3
1>
1%
#616
0%
#617
1%
#618
0%
#619
1%
#620
0%
0(
#621
0?
1%
#622
0%
#623
0=
1%
#624
0%
#625
0>
1%
#626
0%
#627
1%
#628
0%
#629
1%
#630
0%
1(
#631
1?
1%
#632
0%
#633
1=
1%
#634
0%
#635
b110 ,
b11111111 3
1>
1%
#636
0%
#637
1%
#638
0%
#639
1%
#640
0%
0(
#641
0?
1%
#642
0%
#643
0=
1%
#644
0%
#645
0>
1%
#646
0%
#647
1%
#648
0%
#649
1%
#650
0%
1(
#651
1?
1%
#652
0%
#653
1=
1%
#654
0%
#655
b111 ,
1>
1%
#656
0%
#657
1%
#658
0%
#659
1%
#660
0%
0(
#661
0?
1%
#662
0%
#663
0=
1%
#664
0%
#665
0>
1%
#666
0%
#667
1%
#668
0%
#669
1%
#670
0%
1(
#671
1?
1%
#672
0%
#673
1=
1%
#674
0%
#675
b1000 ,
1>
1%
#676
0%
#677
b100 @
b11111111 /
1D
1%
#678
0%
#679
0D
b11111111 7
1%
#680
0%
0(
#681
0?
b11111111 #
b11111111 -
1%
#682
0%
#683
0=
1%
#684
0%
#685
0>
1%
